{
  "ComponentIndexes": {
    "cmpLoginFail": 31,
    "cmpScreenSuccess": 32,
    "cmpTransitionLoad": 33,
    "FooterCompany": 34,
    "FooterWorker": 35,
    "HeaderCompany": 36,
    "HeaderWorker": 37,
    "SuccessModalOnlyOKButton": 38,
    "testGlobalVariables": 39
  },
  "ControlUniqueGuids": {},
  "ControlUniqueIds": {
    "Alterar_Projeto_empresa": 421,
    "App": 1,
    "AppTittle": 385,
    "Atividade_alterada_colaborador": 529,
    "Atividade_criada_colaborador": 535,
    "atualizar_dados_empresa": 541,
    "BackgroundFooterDark": 23,
    "BackgroundFooterLight": 20,
    "BackgroundHeaderDark": 26,
    "BackgroundHeaderDark_2": 31,
    "BackImage": 379,
    "Body1": 304,
    "Body3": 452,
    "BodyToEmailTextInput": 418,
    "Buscar_por_colaboradores_empresa": 569,
    "Buscar_por_projeto_empresa": 582,
    "Button1": 44,
    "Button2": 420,
    "Button4": 45,
    "ButtonActivitiesWorker": 319,
    "ButtonBack": 309,
    "ButtonBack_1": 521,
    "ButtonBack_3": 435,
    "ButtonBack_4": 256,
    "ButtonBack_5": 288,
    "ButtonCreateActivityWorker": 318,
    "ButtonCreateProjectCompany": 335,
    "ButtonCreateProjectWorker": 323,
    "ButtonCreateUserCompany": 70,
    "ButtonCreateUserWorker": 622,
    "ButtonDirectWorker": 338,
    "ButtonDisable_1": 566,
    "ButtonDisable_2": 436,
    "ButtonDisable_3": 257,
    "ButtonDisable_4": 289,
    "ButtonDownload": 310,
    "ButtonDownload_1": 522,
    "ButtonDownload_2": 459,
    "ButtonEditActivity": 476,
    "ButtonEditProject": 511,
    "ButtonEditUserCompany": 334,
    "ButtonEditUserWorker": 322,
    "ButtonHome_1": 592,
    "ButtonHome_2": 401,
    "ButtonHome_3": 579,
    "ButtonHome_4": 89,
    "ButtonHome_6": 76,
    "ButtonHome_7": 207,
    "ButtonHome_8": 565,
    "ButtonHome_9": 161,
    "ButtonHomeWorker_10": 121,
    "ButtonHomeWorker_3": 374,
    "ButtonHomeWorker_4": 538,
    "ButtonHomeWorker_5": 458,
    "ButtonHomeWorker_6": 465,
    "ButtonHomeWorker_7": 82,
    "ButtonHomeWorker_8": 532,
    "ButtonHomeWorker_9": 406,
    "ButtonLogin": 393,
    "ButtonProjects": 330,
    "ButtonRegistration": 392,
    "ButtonRegistration_1": 103,
    "ButtonRegistration_2": 96,
    "ButtonSave_1": 567,
    "ButtonSave_2": 437,
    "ButtonSave_3": 162,
    "ButtonSave_4": 208,
    "ButtonSave_5": 258,
    "ButtonSave_6": 290,
    "ButtonSaveWorker_1": 375,
    "ButtonSaveWorker_2": 122,
    "ButtonWorkers": 331,
    "cadastro_colaborador": 595,
    "cadastro_empresa": 47,
    "cmpLoginFail": 3,
    "cmpLoginFail_1": 380,
    "cmpScreenSuccess": 9,
    "cmpScreenSuccess_1": 383,
    "cmpTransitionLoad": 14,
    "cmpTransitionLoadLogin": 382,
    "cnpj_DataCard1": 50,
    "cnpj_DataCard1_1": 545,
    "cnpj_DataCard2": 470,
    "Colaborador": 294,
    "colaborador_alocado_empresa": 72,
    "ComboBox1": 677,
    "Conta_Alterada_colaborador": 79,
    "Conta_Alterada_empresa": 85,
    "Conta_criada_colaborador": 92,
    "Conta_criada_empresa": 99,
    "Container1": 40,
    "cpf_DataCard2": 597,
    "cpf_DataCard2_1": 263,
    "criar_Projeto_colaborador": 106,
    "criar_Projeto_empresa": 125,
    "DataCardKey10": 500,
    "DataCardKey11": 503,
    "DataCardKey12": 506,
    "DataCardKey13": 426,
    "DataCardKey13_1": 131,
    "DataCardKey13_2": 110,
    "DataCardKey15": 619,
    "DataCardKey15_1": 285,
    "DataCardKey16": 431,
    "DataCardKey16_1": 136,
    "DataCardKey16_2": 115,
    "DataCardKey17": 351,
    "DataCardKey17_1": 233,
    "DataCardKey18": 356,
    "DataCardKey18_1": 238,
    "DataCardKey19": 361,
    "DataCardKey19_1": 243,
    "DataCardKey2": 51,
    "DataCardKey2_1": 546,
    "DataCardKey20": 366,
    "DataCardKey20_1": 248,
    "DataCardKey21": 371,
    "DataCardKey21_1": 253,
    "DataCardKey22_1": 678,
    "DataCardKey23": 509,
    "DataCardKey27": 481,
    "DataCardKey28": 484,
    "DataCardKey29": 487,
    "DataCardKey3": 56,
    "DataCardKey3_1": 551,
    "DataCardKey30": 490,
    "DataCardKey31": 493,
    "DataCardKey4": 61,
    "DataCardKey4_1": 556,
    "DataCardKey5": 598,
    "DataCardKey5_1": 264,
    "DataCardKey56": 471,
    "DataCardKey57": 468,
    "DataCardKey58": 474,
    "DataCardKey6": 604,
    "DataCardKey6_1": 270,
    "DataCardKey7": 66,
    "DataCardKey7_1": 561,
    "DataCardKey8": 609,
    "DataCardKey8_1": 275,
    "DataCardKey9": 614,
    "DataCardKey9_1": 280,
    "DataCardValue10": 504,
    "DataCardValue11": 507,
    "DataCardValue12": 615,
    "DataCardValue12_1": 281,
    "DataCardValue14": 428,
    "DataCardValue14_1": 133,
    "DataCardValue14_2": 112,
    "DataCardValue15": 620,
    "DataCardValue15_1": 286,
    "DataCardValue16": 433,
    "DataCardValue16_1": 138,
    "DataCardValue16_2": 117,
    "DataCardValue17": 352,
    "DataCardValue17_1": 234,
    "DataCardValue18": 357,
    "DataCardValue18_1": 239,
    "DataCardValue19": 362,
    "DataCardValue19_1": 244,
    "DataCardValue2": 53,
    "DataCardValue2_1": 548,
    "DataCardValue20": 367,
    "DataCardValue20_1": 249,
    "DataCardValue21": 372,
    "DataCardValue21_1": 254,
    "DataCardValue23": 510,
    "DataCardValue27": 482,
    "DataCardValue28": 485,
    "DataCardValue29": 488,
    "DataCardValue3": 58,
    "DataCardValue3_1": 553,
    "DataCardValue30": 491,
    "DataCardValue31": 494,
    "DataCardValue4": 63,
    "DataCardValue4_1": 558,
    "DataCardValue5": 600,
    "DataCardValue5_1": 266,
    "DataCardValue56": 472,
    "DataCardValue57": 469,
    "DataCardValue58": 475,
    "DataCardValue6": 605,
    "DataCardValue6_1": 271,
    "DataCardValue7": 68,
    "DataCardValue7_1": 563,
    "DataCardValue8": 610,
    "DataCardValue8_1": 276,
    "DataCardValue9": 501,
    "DataTable2": 176,
    "date_DataCard1": 364,
    "date_DataCard1_1": 246,
    "date_DataCard3": 489,
    "description_DataCard1": 354,
    "description_DataCard1_1": 236,
    "description_DataCard3": 483,
    "Designar_colaborador_empresa": 166,
    "DropdownCompany": 345,
    "DropdownCompany_1": 227,
    "DropdownCompany_2": 120,
    "DropdownCompany_3": 444,
    "DropdownMonth": 298,
    "DropdownMonth_1": 446,
    "DropdownProject": 347,
    "DropdownProject_1": 229,
    "editar_atividade_colaborador_1": 224,
    "editar_cadastro_colaborador": 260,
    "email_DataCard1": 473,
    "email_DataCard2": 60,
    "email_DataCard2_1": 555,
    "email_DataCard3": 612,
    "email_DataCard3_1": 278,
    "ErrorMessage13": 429,
    "ErrorMessage13_1": 134,
    "ErrorMessage13_2": 113,
    "ErrorMessage15": 621,
    "ErrorMessage15_1": 287,
    "ErrorMessage16": 434,
    "ErrorMessage16_1": 139,
    "ErrorMessage16_2": 118,
    "ErrorMessage17": 353,
    "ErrorMessage17_1": 235,
    "ErrorMessage18": 358,
    "ErrorMessage18_1": 240,
    "ErrorMessage19": 363,
    "ErrorMessage19_1": 245,
    "ErrorMessage2": 54,
    "ErrorMessage2_1": 549,
    "ErrorMessage20": 368,
    "ErrorMessage20_1": 250,
    "ErrorMessage21": 373,
    "ErrorMessage21_1": 255,
    "ErrorMessage3": 59,
    "ErrorMessage3_1": 554,
    "ErrorMessage4": 64,
    "ErrorMessage4_1": 559,
    "ErrorMessage5": 601,
    "ErrorMessage5_1": 267,
    "ErrorMessage6": 606,
    "ErrorMessage6_1": 272,
    "ErrorMessage7": 69,
    "ErrorMessage7_1": 564,
    "ErrorMessage8": 611,
    "ErrorMessage8_1": 277,
    "ErrorMessage9": 616,
    "ErrorMessage9_1": 282,
    "FooterCompany": 19,
    "FooterCompany_1": 341,
    "FooterCompany_10": 438,
    "FooterCompany_11": 164,
    "FooterCompany_12": 568,
    "FooterCompany_13": 581,
    "FooterCompany_14": 594,
    "FooterCompany_15": 71,
    "FooterCompany_2": 314,
    "FooterCompany_3": 526,
    "FooterCompany_4": 91,
    "FooterCompany_5": 105,
    "FooterCompany_6": 403,
    "FooterCompany_7": 413,
    "FooterCompany_8": 78,
    "FooterCompany_9": 221,
    "FooterWorker": 22,
    "FooterWorker_1": 327,
    "FooterWorker_10": 495,
    "FooterWorker_11": 259,
    "FooterWorker_12": 291,
    "FooterWorker_13": 124,
    "FooterWorker_2": 84,
    "FooterWorker_3": 534,
    "FooterWorker_4": 98,
    "FooterWorker_5": 540,
    "FooterWorker_6": 408,
    "FooterWorker_7": 623,
    "FooterWorker_8": 377,
    "FooterWorker_9": 462,
    "FormActivity": 348,
    "FormActivity_1": 230,
    "FormCompanyReg": 49,
    "FormCompanyReg_1": 544,
    "FormProjectCreate_1": 129,
    "FormProjectCreate_2": 108,
    "FormProjectEdit": 424,
    "FormViewerCompany": 466,
    "FormViewerProject1": 498,
    "FormViewerTasks": 479,
    "FormWorkerEdit": 262,
    "FormWorkerReg": 596,
    "Gallery2": 299,
    "Gallery3": 184,
    "Gallery5": 512,
    "Gallery7": 447,
    "GalleryCollaborators": 574,
    "GalleryProject": 587,
    "galleryTemplate1": 588,
    "galleryTemplate2": 575,
    "galleryTemplate4": 300,
    "galleryTemplate5": 185,
    "galleryTemplate7": 513,
    "galleryTemplate9": 448,
    "Group": 21,
    "Group_1": 24,
    "Group1": 316,
    "Group1_1": 457,
    "Group2_1": 165,
    "Group3": 223,
    "Group7": 222,
    "HeaderCompany": 25,
    "HeaderCompany_1": 329,
    "HeaderCompany_10": 126,
    "HeaderCompany_11": 542,
    "HeaderCompany_12": 570,
    "HeaderCompany_13": 583,
    "HeaderCompany_14": 100,
    "HeaderCompany_2": 293,
    "HeaderCompany_3": 497,
    "HeaderCompany_4": 86,
    "HeaderCompany_5": 398,
    "HeaderCompany_6": 410,
    "HeaderCompany_7": 73,
    "HeaderCompany_8": 167,
    "HeaderCompany_9": 422,
    "HeaderCompany_cad_empresa": 48,
    "HeaderCompany_cad_empresa_1": 168,
    "HeaderWorker": 30,
    "Horas_por_Colaborador_empresa": 292,
    "hours_DataCard1": 369,
    "hours_DataCard1_1": 251,
    "hours_DataCard3": 492,
    "HoursProjectCard": 528,
    "Icon19": 104,
    "Icon19_1": 97,
    "Icon19_10": 220,
    "Icon19_11": 163,
    "Icon19_12": 460,
    "Icon19_13": 478,
    "Icon19_14": 83,
    "Icon19_15": 533,
    "Icon19_16": 407,
    "Icon19_17": 123,
    "Icon19_2": 376,
    "Icon19_3": 593,
    "Icon19_4": 402,
    "Icon19_5": 90,
    "Icon19_6": 412,
    "Icon19_7": 580,
    "Icon19_8": 77,
    "Icon19_9": 539,
    "Icon2": 419,
    "Icon7": 313,
    "Icon7_1": 312,
    "Icon7_2": 525,
    "Icon7_3": 524,
    "IconActivities": 321,
    "IconAddActivity": 320,
    "IconAddProject": 325,
    "IconAddProjectCompany": 337,
    "IconBack": 315,
    "IconBack_1": 527,
    "iconCheck1_4": 12,
    "iconCircle1_4": 11,
    "iconCircleIcon": 6,
    "IconDirectWorker": 339,
    "IconDownload": 311,
    "IconDownload_1": 523,
    "IconDownload_2": 461,
    "IconLeft": 27,
    "IconLeft_2": 32,
    "iconMidlleScreen": 7,
    "IconProjects": 332,
    "IconRight": 29,
    "IconRight_2": 34,
    "IconSearch1": 586,
    "IconSearch1_1": 573,
    "IconUserCompany": 336,
    "IconUserWorker": 324,
    "IconWorkers": 333,
    "Image1": 17,
    "Image2": 326,
    "Image28949": 206,
    "Image28956": 202,
    "Image28963": 198,
    "Image28970": 194,
    "Image28981": 190,
    "Image341256": 536,
    "Image341287_1": 160,
    "Image341294_1": 156,
    "Image341301_1": 152,
    "Image341308_1": 148,
    "Image341319_1": 144,
    "Image341381": 87,
    "Image341381_1": 80,
    "Image371666": 411,
    "Image371666_1": 405,
    "Image371667": 74,
    "Image371668": 399,
    "Image371669": 530,
    "Image381685": 101,
    "Image381685_1": 94,
    "Image381796": 340,
    "ImgLoadLogin_1": 441,
    "infCont": 37,
    "inicial_colaborador": 317,
    "inicial_empresa": 328,
    "inputSearchProjectByName": 183,
    "inserir_atividade_colaborador": 342,
    "Label1": 384,
    "Label2": 391,
    "Label20323": 308,
    "Label20323_1": 456,
    "Label20324": 307,
    "Label20324_1": 455,
    "Label20480": 295,
    "Label20480_1": 296,
    "Label281068": 75,
    "Label281087_6": 38,
    "Label28951": 205,
    "Label28958": 201,
    "Label28965": 197,
    "Label28972": 193,
    "Label28977": 189,
    "Label28982": 186,
    "Label3": 41,
    "Label341255": 537,
    "Label341271": 531,
    "Label341289_1": 159,
    "Label341296_1": 155,
    "Label341303_1": 151,
    "Label341310_1": 147,
    "Label341315_1": 143,
    "Label341320_1": 140,
    "Label341365": 400,
    "Label341380": 88,
    "Label341380_1": 81,
    "Label381684": 102,
    "Label381684_1": 95,
    "Label5": 43,
    "LabelCompanyName": 344,
    "LabelCompanyName_1": 226,
    "LabelCompanyName_2": 119,
    "LabelLoginError": 388,
    "LabelPasswordError": 390,
    "LabelProjectName": 346,
    "LabelProjectName_1": 228,
    "LabelProjectName_2": 477,
    "lblLoadingMsgMiddleScreen": 18,
    "LblSuccessMsg1_4": 13,
    "lblSuccessMsgMiddleScreen": 8,
    "login": 378,
    "mainContainer": 4,
    "mainContainer_1": 15,
    "manager_Column1": 178,
    "manager_DataCard1": 430,
    "manager_DataCard1_1": 135,
    "manager_DataCard1_2": 114,
    "manager_DataCard2": 502,
    "modalSuccess": 36,
    "MonthLabel": 297,
    "MonthLabel_1": 445,
    "name_Column1": 177,
    "name_DataCard1": 499,
    "name_DataCard2": 55,
    "name_DataCard2_1": 550,
    "name_DataCard3": 602,
    "name_DataCard3_1": 268,
    "name_DataCard4": 425,
    "name_DataCard4_1": 130,
    "name_DataCard4_2": 109,
    "name_DataCard5": 349,
    "name_DataCard5_1": 231,
    "name_DataCard6": 480,
    "name_DataCard7": 467,
    "NameLogin_2": 28,
    "NameLogin_3": 33,
    "NextArrow1": 626,
    "NextArrow12": 451,
    "NextArrow4": 303,
    "NextArrow5": 576,
    "NextArrow8": 515,
    "NextArrow8_1": 634,
    "password_DataCard1": 65,
    "password_DataCard1_1": 560,
    "password_DataCard2": 617,
    "password_DataCard2_1": 283,
    "ProjectsLabel": 584,
    "ProjectsLabel_1": 571,
    "Projeto_alterado_empresa": 397,
    "Projeto_criado_colaborador": 404,
    "Projeto_criado_empresa": 409,
    "rect": 381,
    "Rectangle1": 46,
    "Rectangle20308_4": 93,
    "Rectangle20322": 306,
    "Rectangle20322_1": 519,
    "Rectangle20322_2": 454,
    "Rectangle28947": 204,
    "Rectangle28950": 203,
    "Rectangle28954": 200,
    "Rectangle28957": 199,
    "Rectangle28961": 196,
    "Rectangle28964": 195,
    "Rectangle28968": 192,
    "Rectangle28971": 191,
    "Rectangle28973": 187,
    "Rectangle28979": 188,
    "Rectangle3_4": 10,
    "Rectangle341285_1": 158,
    "Rectangle341288_1": 157,
    "Rectangle341292_1": 154,
    "Rectangle341295_1": 153,
    "Rectangle341299_1": 150,
    "Rectangle341302_1": 149,
    "Rectangle341306_1": 146,
    "Rectangle341309_1": 145,
    "Rectangle341311_1": 141,
    "Rectangle341317_1": 142,
    "rectContainer": 5,
    "rectContainer_1": 16,
    "Scr_teste_envio_email": 414,
    "SearchBox": 585,
    "SearchBox_1": 572,
    "SendFromEmailTextInput": 415,
    "SendToEmailTextInput": 416,
    "Separator1": 627,
    "Separator12": 453,
    "Separator4": 305,
    "Separator5": 578,
    "Separator8": 517,
    "splash": 439,
    "start_DataCard1": 505,
    "StarVisible13": 427,
    "StarVisible13_1": 132,
    "StarVisible13_2": 111,
    "StarVisible15": 618,
    "StarVisible15_1": 284,
    "StarVisible16": 432,
    "StarVisible16_1": 137,
    "StarVisible16_2": 116,
    "StarVisible17": 350,
    "StarVisible17_1": 232,
    "StarVisible18": 355,
    "StarVisible18_1": 237,
    "StarVisible19": 360,
    "StarVisible19_1": 242,
    "StarVisible2": 52,
    "StarVisible2_1": 547,
    "StarVisible20": 365,
    "StarVisible20_1": 247,
    "StarVisible21": 370,
    "StarVisible21_1": 252,
    "StarVisible3": 57,
    "StarVisible3_1": 552,
    "StarVisible4": 62,
    "StarVisible4_1": 557,
    "StarVisible5": 599,
    "StarVisible5_1": 265,
    "StarVisible6": 603,
    "StarVisible6_1": 269,
    "StarVisible7": 67,
    "StarVisible7_1": 562,
    "StarVisible8": 608,
    "StarVisible8_1": 274,
    "StarVisible9": 613,
    "StarVisible9_1": 279,
    "status_Column1": 181,
    "status_DataCard1": 359,
    "status_DataCard1_1": 241,
    "status_DataCard2": 508,
    "status_DataCard3": 486,
    "SubjToEmailTextInput": 417,
    "Subtitle1": 625,
    "Subtitle1_1": 630,
    "Subtitle3": 302,
    "Subtitle5": 516,
    "Subtitle9": 450,
    "SuccessModalOnlyOKButton": 35,
    "SuccessModalOnlyOKButton_1": 127,
    "tempScreenTransitionErrorFase": 396,
    "tempScreenTransitionFase1": 394,
    "tempScreenTransitionFase2": 395,
    "testGlobalVariables": 39,
    "Timer2": 440,
    "Timer3": 42,
    "Title1": 624,
    "Title1_1": 629,
    "Title12": 449,
    "Title4": 301,
    "Title5": 577,
    "Title8": 514,
    "TitleActivity": 464,
    "TitleCreateActivity": 343,
    "TitleEditAccount": 261,
    "TitleEditActivity": 225,
    "TitlePage_2": 543,
    "TitlePage_3": 423,
    "TitlePage_4": 128,
    "TitlePage_5": 107,
    "TitlePage_Choose": 169,
    "TitleViewActivity": 443,
    "Toggle_Cpf_Or_Cnpj": 386,
    "TotalHoursProject": 520,
    "TotalHoursProjectLabel": 518,
    "TxtInputLoginCnpj_Cpf": 387,
    "TxtInputLoginSenha": 389,
    "username_DataCard1": 607,
    "username_DataCard1_1": 273,
    "visualizar_atividades_colaborador": 442,
    "visualizar_evento_colaborador": 463,
    "Visualizar_Projeto_empresa": 496
  },
  "FunctionParamsInvariantScripts": {},
  "FunctionParamsInvariantScriptsOnInstances": {},
  "HeaderLastSavedDateTimeUTC": "11/24/2022 17:31:52",
  "IsLegacyComponentAllowGlobalScopeCase": false,
  "LocalConnectionIDReferences": {
    "0231a2ce-81a0-4ca3-abe3-d1a85fafc381": "\"/providers/microsoft.powerapps/apis/shared_logicflows/connections/c77198d0-0185-4d36-b043-768262e218b6\"",
    "3fa69c61-3796-4c93-9ef8-e4a01d17587d": "\"/providers/microsoft.powerapps/apis/shared_sharepointonline/connections/baf4421f5d534f47a16758ea4845733e\"",
    "e9312235-b10c-467c-b556-e87d7fdaa901": "\"/providers/microsoft.powerapps/apis/shared_office365/connections/shared-office365-fa33c161-58a9-473d-8591-3352f15d6fda\""
  },
  "LocalDatabaseReferencesAsEmpty": false,
  "LocalResourceFileNames": {
    "business-people-rush-hour-walking-commuting-city-concept": "0002.jpg",
    "business-people-rush-hour-walking-commuting-city-concept-cut": "0001.jpg",
    "business-people-rush-hour-walking-commuting-city-concepts": "0003.jpg",
    "icons8-dots-loading": "0004.gif",
    "image1835": "0005.png",
    "image1836": "0006.png",
    "image1838": "0007.png",
    "image1842": "0008.png",
    "image1844": "0009.png",
    "image1846": "0010.png",
    "image20128": "0011.png",
    "image20131": "0012.png",
    "image20137": "0013.png",
    "image20139": "0014.png",
    "image20179": "0015.png",
    "image20232": "0016.png",
    "image20238": "0017.png",
    "image20240": "0018.png",
    "image20242": "0019.png",
    "image20244": "0020.png",
    "image20290": "0021.png",
    "image20302": "0022.png",
    "image20310": "0023.png",
    "image20316": "0024.png",
    "image20320": "0025.png",
    "image20348": "0026.png",
    "image20354": "0027.png",
    "image20391": "0028.png",
    "image20469": "0029.png",
    "image20474": "0030.png",
    "image20479": "0031.png",
    "image20509": "0032.png",
    "image20621": "0033.png",
    "image2066": "0034.png",
    "image20706": "0035.png",
    "image20711": "0036.png",
    "image20724": "0037.png",
    "image20729": "0038.png",
    "image20750": "0039.png",
    "image2078": "0040.png",
    "image216": "0041.png",
    "image281011": "0042.png",
    "image281064": "0043.png",
    "image281080": "0044.png",
    "image281086": "0045.png",
    "image281103": "0046.png",
    "image281106": "0047.png",
    "image28789": "0048.png",
    "image28793": "0049.png",
    "image28828": "0050.png",
    "image28831": "0051.png",
    "image28852": "0052.png",
    "image28884": "0053.png",
    "image28903": "0054.png",
    "image28931": "0055.png",
    "image28942": "0056.png",
    "image28949": "0057.png",
    "image28956": "0058.png",
    "image28963": "0059.png",
    "image28970": "0060.png",
    "image28976": "0061.png",
    "image28981": "0062.png",
    "image28995": "0063.png",
    "image341155": "0064.png",
    "image341169": "0065.png",
    "image341191": "0066.png",
    "image341196": "0067.png",
    "image341202": "0068.png",
    "image341207": "0069.png",
    "image341222": "0070.png",
    "image341248": "0071.png",
    "image341254": "0072.png",
    "image341256": "0073.png",
    "image341264": "0074.png",
    "image341270": "0075.png",
    "image341280": "0076.png",
    "image341287": "0077.png",
    "image341294": "0078.png",
    "image341301": "0079.png",
    "image341308": "0080.png",
    "image341314": "0081.png",
    "image341319": "0082.png",
    "image341345": "0083.png",
    "image341358": "0084.png",
    "image341364": "0085.png",
    "image341379": "0086.png",
    "image341381": "0087.png",
    "image361394": "0088.png",
    "image361400": "0089.png",
    "image361401": "0090.png",
    "image361402": "0091.png",
    "image361403": "0092.png",
    "image361404": "0093.png",
    "image361405": "0094.png",
    "image361406": "0095.png",
    "image361411": "0096.png",
    "image361479": "0097.png",
    "image361482": "0098.png",
    "image361485": "0099.png",
    "image371504": "0100.png",
    "image371506": "0101.png",
    "image371519": "0102.png",
    "image371572": "0103.png",
    "image371584": "0104.png",
    "image371618": "0105.png",
    "image371637": "0106.png",
    "image371646": "0107.png",
    "image371662": "0108.png",
    "image371666": "0109.png",
    "image371667": "0110.png",
    "image371668": "0111.png",
    "image371669": "0112.png",
    "image381683": "0113.png",
    "image381685": "0114.png",
    "image381693": "0115.png",
    "image381699": "0116.png",
    "image381701": "0117.png",
    "image381709": "0118.png",
    "image381715": "0119.png",
    "image381718": "0120.png",
    "image381731": "0121.png",
    "image381733": "0122.png",
    "image381737": "0123.png",
    "image381746": "0124.png",
    "image381768": "0125.png",
    "image381773": "0126.png",
    "image381784": "0127.png",
    "image381789": "0128.png",
    "image381793": "0129.png",
    "image381796": "0130.png",
    "image381850": "0131.png",
    "image381863": "0132.png",
    "image381870": "0133.png",
    "image381875": "0134.png",
    "image582108": "0135.png",
    "image582167": "0136.png",
    "image8150": "0137.png",
    "time-is-money-sandglass-investment-countdown-measure-concept": "0138.jpg"
  },
  "LocalResourceRootPaths": {
    "business-people-rush-hour-walking-commuting-city-concept": "https://docserverpwaprodwus.blob.core.windows.net/85cb91a0-136e-43ce-b7be-ed7c25df8283-1/resource/Assets0Images00002.jpg?sv=2017-04-17&sr=b&sig=JHJBCLaoEReBQTOSMXP8zVVKZrLQ7NxPJbLXROSZgzw%3D&spr=https&se=2022-11-25T16%3A24%3A35Z&sp=r",
    "business-people-rush-hour-walking-commuting-city-concept-cut": "https://docserverpwaprodwus.blob.core.windows.net/85cb91a0-136e-43ce-b7be-ed7c25df8283-1/resource/Assets0Images00001.jpg?sv=2017-04-17&sr=b&sig=2d8YlwkApeeuvFhim%2FZHNVS9lrjptI026DuJR5fEwzw%3D&spr=https&se=2022-11-25T16%3A24%3A35Z&sp=r",
    "business-people-rush-hour-walking-commuting-city-concepts": "https://docserverpwaprodwus.blob.core.windows.net/85cb91a0-136e-43ce-b7be-ed7c25df8283-1/resource/Assets0Images00003.jpg?sv=2017-04-17&sr=b&sig=fnP%2FzcQn0Oebd25wZui7870on9OjtqzbOkDl3dQSETg%3D&spr=https&se=2022-11-25T16%3A24%3A35Z&sp=r",
    "icons8-dots-loading": "https://docserverpwaprodwus.blob.core.windows.net/85cb91a0-136e-43ce-b7be-ed7c25df8283-1/resource/Assets0Images00004.gif?sv=2017-04-17&sr=b&sig=mQ2t9Gd3xua9EZs%2BGT5AnNtyQDBm%2FVnyRSSIWMan3j4%3D&spr=https&se=2022-11-25T16%3A24%3A35Z&sp=r",
    "image1835": "https://docserverpwaprodwus.blob.core.windows.net/85cb91a0-136e-43ce-b7be-ed7c25df8283-1/resource/Assets0Images00005.png?sv=2017-04-17&sr=b&sig=TWypwiRvQ2xo2r3P04%2BxZkduh6tYnVTOOXdgdSouNXI%3D&spr=https&se=2022-11-25T16%3A24%3A35Z&sp=r",
    "image1836": "https://docserverpwaprodwus.blob.core.windows.net/85cb91a0-136e-43ce-b7be-ed7c25df8283-1/resource/Assets0Images00006.png?sv=2017-04-17&sr=b&sig=F1%2FNsaaClaYsOuixSVt3D785yRu6GgkxakhZMY9VmuI%3D&spr=https&se=2022-11-25T16%3A24%3A35Z&sp=r",
    "image1838": "https://docserverpwaprodwus.blob.core.windows.net/85cb91a0-136e-43ce-b7be-ed7c25df8283-1/resource/Assets0Images00007.png?sv=2017-04-17&sr=b&sig=Dv8%2BiLB7WXeVl0UsyhDZAW1RK7GwXi6m7GhBhRvFl58%3D&spr=https&se=2022-11-25T16%3A24%3A35Z&sp=r",
    "image1842": "https://docserverpwaprodwus.blob.core.windows.net/85cb91a0-136e-43ce-b7be-ed7c25df8283-1/resource/Assets0Images00008.png?sv=2017-04-17&sr=b&sig=8%2BawKVVr3PqJitzIWBY5JezEJCVRiwcM8iQxmaLIBN8%3D&spr=https&se=2022-11-25T16%3A24%3A35Z&sp=r",
    "image1844": "https://docserverpwaprodwus.blob.core.windows.net/85cb91a0-136e-43ce-b7be-ed7c25df8283-1/resource/Assets0Images00009.png?sv=2017-04-17&sr=b&sig=X0793OmFspSu8jaPR2nqypbh1uz5gbWtS62jFr4pKYY%3D&spr=https&se=2022-11-25T16%3A24%3A35Z&sp=r",
    "image1846": "https://docserverpwaprodwus.blob.core.windows.net/85cb91a0-136e-43ce-b7be-ed7c25df8283-1/resource/Assets0Images00010.png?sv=2017-04-17&sr=b&sig=74%2BjlMZEszeUEZA5tlzU8VIpcUSzj5D3wzfVQOYkkIk%3D&spr=https&se=2022-11-25T16%3A24%3A35Z&sp=r",
    "image20128": "https://docserverpwaprodwus.blob.core.windows.net/85cb91a0-136e-43ce-b7be-ed7c25df8283-1/resource/Assets0Images00011.png?sv=2017-04-17&sr=b&sig=lLIZ%2B8z5TxqUE16pl5SBRbYZ%2BNr7wZ87cNV6Xm3HKz4%3D&spr=https&se=2022-11-25T16%3A24%3A35Z&sp=r",
    "image20131": "https://docserverpwaprodwus.blob.core.windows.net/85cb91a0-136e-43ce-b7be-ed7c25df8283-1/resource/Assets0Images00012.png?sv=2017-04-17&sr=b&sig=RissF%2FuUH9xWgz79rhgUM0Gm3eTHK06y2%2BIV%2Fbc5Kt8%3D&spr=https&se=2022-11-25T16%3A24%3A35Z&sp=r",
    "image20137": "https://docserverpwaprodwus.blob.core.windows.net/85cb91a0-136e-43ce-b7be-ed7c25df8283-1/resource/Assets0Images00013.png?sv=2017-04-17&sr=b&sig=cWf6BX27j76FI%2BliRPUcNKip13mn83aHYFmIM96tYO4%3D&spr=https&se=2022-11-25T16%3A24%3A35Z&sp=r",
    "image20139": "https://docserverpwaprodwus.blob.core.windows.net/85cb91a0-136e-43ce-b7be-ed7c25df8283-1/resource/Assets0Images00014.png?sv=2017-04-17&sr=b&sig=H41F1hSiZccciLNV9LDDDn2%2FtDcH9Zb%2FQ8IIxEAs%2FDg%3D&spr=https&se=2022-11-25T16%3A24%3A35Z&sp=r",
    "image20179": "https://docserverpwaprodwus.blob.core.windows.net/85cb91a0-136e-43ce-b7be-ed7c25df8283-1/resource/Assets0Images00015.png?sv=2017-04-17&sr=b&sig=O8hzn2rpOL8uelVpzO1Ws7UQlMDxSYJH9pezlt%2BmldQ%3D&spr=https&se=2022-11-25T16%3A24%3A35Z&sp=r",
    "image20232": "https://docserverpwaprodwus.blob.core.windows.net/85cb91a0-136e-43ce-b7be-ed7c25df8283-1/resource/Assets0Images00016.png?sv=2017-04-17&sr=b&sig=hHLt5NgcAUtIljUoPtunfPzL2Eme8Vv2zG1JTUrt8yI%3D&spr=https&se=2022-11-25T16%3A24%3A35Z&sp=r",
    "image20238": "https://docserverpwaprodwus.blob.core.windows.net/85cb91a0-136e-43ce-b7be-ed7c25df8283-1/resource/Assets0Images00017.png?sv=2017-04-17&sr=b&sig=oViiqFSqH22%2FaVZUkr8eUPp59TzODuEwDxwidHtFeF8%3D&spr=https&se=2022-11-25T16%3A24%3A35Z&sp=r",
    "image20240": "https://docserverpwaprodwus.blob.core.windows.net/85cb91a0-136e-43ce-b7be-ed7c25df8283-1/resource/Assets0Images00018.png?sv=2017-04-17&sr=b&sig=GZyIS6gsSqLsQnvxPsKMWh3HrO%2FFGbHEXXe7gabTzDM%3D&spr=https&se=2022-11-25T16%3A24%3A35Z&sp=r",
    "image20242": "https://docserverpwaprodwus.blob.core.windows.net/85cb91a0-136e-43ce-b7be-ed7c25df8283-1/resource/Assets0Images00019.png?sv=2017-04-17&sr=b&sig=uTqJinmN5jl37haz7BQlL%2FxWnM8sLTtSjZ73oOhL2d0%3D&spr=https&se=2022-11-25T16%3A24%3A35Z&sp=r",
    "image20244": "https://docserverpwaprodwus.blob.core.windows.net/85cb91a0-136e-43ce-b7be-ed7c25df8283-1/resource/Assets0Images00020.png?sv=2017-04-17&sr=b&sig=2Rbi4qyMZe9xYbamAIXDjrykklLp5gea92bR0ivotj4%3D&spr=https&se=2022-11-25T16%3A24%3A35Z&sp=r",
    "image20290": "https://docserverpwaprodwus.blob.core.windows.net/85cb91a0-136e-43ce-b7be-ed7c25df8283-1/resource/Assets0Images00021.png?sv=2017-04-17&sr=b&sig=8KD3db5T%2BEgygn2WQj%2Fb1KJhCUQBpdJ6v%2F%2FLh3L1jWI%3D&spr=https&se=2022-11-25T16%3A24%3A35Z&sp=r",
    "image20302": "https://docserverpwaprodwus.blob.core.windows.net/85cb91a0-136e-43ce-b7be-ed7c25df8283-1/resource/Assets0Images00022.png?sv=2017-04-17&sr=b&sig=nJ5mpyhcnPKsEU15ZVOINoqgX1OZLMN5%2FrkDii8KpTo%3D&spr=https&se=2022-11-25T16%3A24%3A35Z&sp=r",
    "image20310": "https://docserverpwaprodwus.blob.core.windows.net/85cb91a0-136e-43ce-b7be-ed7c25df8283-1/resource/Assets0Images00023.png?sv=2017-04-17&sr=b&sig=scnR69XW0L3tD53yHcJmRqVAtrVNkxZ%2FMgZRaYTKybI%3D&spr=https&se=2022-11-25T16%3A24%3A35Z&sp=r",
    "image20316": "https://docserverpwaprodwus.blob.core.windows.net/85cb91a0-136e-43ce-b7be-ed7c25df8283-1/resource/Assets0Images00024.png?sv=2017-04-17&sr=b&sig=mJ5j4yMNodwdBtKDweYozkeefDgcV%2B%2B600Ry52t74so%3D&spr=https&se=2022-11-25T16%3A24%3A35Z&sp=r",
    "image20320": "https://docserverpwaprodwus.blob.core.windows.net/85cb91a0-136e-43ce-b7be-ed7c25df8283-1/resource/Assets0Images00025.png?sv=2017-04-17&sr=b&sig=dj1tw2Wd%2FatOElqJZF3sVnGdB5J4OdaUZ5xfNYhU800%3D&spr=https&se=2022-11-25T16%3A24%3A35Z&sp=r",
    "image20348": "https://docserverpwaprodwus.blob.core.windows.net/85cb91a0-136e-43ce-b7be-ed7c25df8283-1/resource/Assets0Images00026.png?sv=2017-04-17&sr=b&sig=mUAyQMvZifalNNi7rgR4w0s7EUB5%2FNw2e6hKVAObz1s%3D&spr=https&se=2022-11-25T16%3A24%3A35Z&sp=r",
    "image20354": "https://docserverpwaprodwus.blob.core.windows.net/85cb91a0-136e-43ce-b7be-ed7c25df8283-1/resource/Assets0Images00027.png?sv=2017-04-17&sr=b&sig=yNhOBim3bGpD679ecUSeA0mQ8Oy%2FajKpe8jR6Y7XIiA%3D&spr=https&se=2022-11-25T16%3A24%3A35Z&sp=r",
    "image20391": "https://docserverpwaprodwus.blob.core.windows.net/85cb91a0-136e-43ce-b7be-ed7c25df8283-1/resource/Assets0Images00028.png?sv=2017-04-17&sr=b&sig=7ukrfv1oHt5YuLisDEQ8E86dtl0p5OpXJGrbyntFN4k%3D&spr=https&se=2022-11-25T16%3A24%3A35Z&sp=r",
    "image20469": "https://docserverpwaprodwus.blob.core.windows.net/85cb91a0-136e-43ce-b7be-ed7c25df8283-1/resource/Assets0Images00029.png?sv=2017-04-17&sr=b&sig=xoKOkpmzUwPCqcJIXHNqltNIKet5FLShuLf6gfuNg%2BU%3D&spr=https&se=2022-11-25T16%3A24%3A35Z&sp=r",
    "image20474": "https://docserverpwaprodwus.blob.core.windows.net/85cb91a0-136e-43ce-b7be-ed7c25df8283-1/resource/Assets0Images00030.png?sv=2017-04-17&sr=b&sig=u7EIQNYI9GwVC4Pq%2FXQk0MuivAU%2B9mR70eQsy2nN%2FwY%3D&spr=https&se=2022-11-25T16%3A24%3A35Z&sp=r",
    "image20479": "https://docserverpwaprodwus.blob.core.windows.net/85cb91a0-136e-43ce-b7be-ed7c25df8283-1/resource/Assets0Images00031.png?sv=2017-04-17&sr=b&sig=E6Retm5wgx87kjjBUIX7vjuREWKN3%2BrRbjH4nMU2kQM%3D&spr=https&se=2022-11-25T16%3A24%3A35Z&sp=r",
    "image20509": "https://docserverpwaprodwus.blob.core.windows.net/85cb91a0-136e-43ce-b7be-ed7c25df8283-1/resource/Assets0Images00032.png?sv=2017-04-17&sr=b&sig=SuHdfcZgzImgf2zWXAbxa%2BrubgoimwCRSc3K5%2FqQlFo%3D&spr=https&se=2022-11-25T16%3A24%3A35Z&sp=r",
    "image20621": "https://docserverpwaprodwus.blob.core.windows.net/85cb91a0-136e-43ce-b7be-ed7c25df8283-1/resource/Assets0Images00033.png?sv=2017-04-17&sr=b&sig=IFD9TIAn%2FjOqJYVD1zvkjsuPR0fZOyPTJ9inKUkPz7w%3D&spr=https&se=2022-11-25T16%3A24%3A35Z&sp=r",
    "image2066": "https://docserverpwaprodwus.blob.core.windows.net/85cb91a0-136e-43ce-b7be-ed7c25df8283-1/resource/Assets0Images00034.png?sv=2017-04-17&sr=b&sig=Fy0Nx2C4CRm%2FzOMCv9zUqQPkStHzIdaYrcqTGLgSVAo%3D&spr=https&se=2022-11-25T16%3A24%3A35Z&sp=r",
    "image20706": "https://docserverpwaprodwus.blob.core.windows.net/85cb91a0-136e-43ce-b7be-ed7c25df8283-1/resource/Assets0Images00035.png?sv=2017-04-17&sr=b&sig=mN5mQlk8Ftnc2xxUtOlewcsO%2Bd7FcgUyAMdIZ3XkfyU%3D&spr=https&se=2022-11-25T16%3A24%3A35Z&sp=r",
    "image20711": "https://docserverpwaprodwus.blob.core.windows.net/85cb91a0-136e-43ce-b7be-ed7c25df8283-1/resource/Assets0Images00036.png?sv=2017-04-17&sr=b&sig=75PtaDaNd1U%2BbslXnCTWYHXxOjkysfXNnBLa8mKMJR4%3D&spr=https&se=2022-11-25T16%3A24%3A35Z&sp=r",
    "image20724": "https://docserverpwaprodwus.blob.core.windows.net/85cb91a0-136e-43ce-b7be-ed7c25df8283-1/resource/Assets0Images00037.png?sv=2017-04-17&sr=b&sig=k8r458F9XHi4J%2BPkV%2F48xrtQewvJ4cdI%2BTYLBJ9S0GM%3D&spr=https&se=2022-11-25T16%3A24%3A35Z&sp=r",
    "image20729": "https://docserverpwaprodwus.blob.core.windows.net/85cb91a0-136e-43ce-b7be-ed7c25df8283-1/resource/Assets0Images00038.png?sv=2017-04-17&sr=b&sig=b8qhQA97Pip3C2KpmJm0sagy4V3zydTAwNUnXCAlE0c%3D&spr=https&se=2022-11-25T16%3A24%3A35Z&sp=r",
    "image20750": "https://docserverpwaprodwus.blob.core.windows.net/85cb91a0-136e-43ce-b7be-ed7c25df8283-1/resource/Assets0Images00039.png?sv=2017-04-17&sr=b&sig=8EbKBSs7%2BDLib5NjO56xxA6qvcefk98Wv6rvbiSWff4%3D&spr=https&se=2022-11-25T16%3A24%3A35Z&sp=r",
    "image2078": "https://docserverpwaprodwus.blob.core.windows.net/85cb91a0-136e-43ce-b7be-ed7c25df8283-1/resource/Assets0Images00040.png?sv=2017-04-17&sr=b&sig=DObpaT3xFNjC9zkN3X6nfAhJX7e9XrGNsVL8l5%2Fikq0%3D&spr=https&se=2022-11-25T16%3A24%3A35Z&sp=r",
    "image216": "https://docserverpwaprodwus.blob.core.windows.net/85cb91a0-136e-43ce-b7be-ed7c25df8283-1/resource/Assets0Images00041.png?sv=2017-04-17&sr=b&sig=cx7pACMfEokyJF8nRWnckvYx6QH08xYgp9%2FB5DaW1Jk%3D&spr=https&se=2022-11-25T16%3A24%3A35Z&sp=r",
    "image281011": "https://docserverpwaprodwus.blob.core.windows.net/85cb91a0-136e-43ce-b7be-ed7c25df8283-1/resource/Assets0Images00042.png?sv=2017-04-17&sr=b&sig=w0L33%2B3WKLKR01LzUQ2jxB0E2Vh4EUWPGvPaKSXcSzo%3D&spr=https&se=2022-11-25T16%3A24%3A35Z&sp=r",
    "image281064": "https://docserverpwaprodwus.blob.core.windows.net/85cb91a0-136e-43ce-b7be-ed7c25df8283-1/resource/Assets0Images00043.png?sv=2017-04-17&sr=b&sig=JtIBbJOlYjkK4kcSdUgGgyPGpGDDeZ6hKRy90zF7HLc%3D&spr=https&se=2022-11-25T16%3A24%3A35Z&sp=r",
    "image281080": "https://docserverpwaprodwus.blob.core.windows.net/85cb91a0-136e-43ce-b7be-ed7c25df8283-1/resource/Assets0Images00044.png?sv=2017-04-17&sr=b&sig=Gn9h%2FxP%2FOlVVRySVkpdhzRjSC8Rf9uNhnDDAicj5Q9s%3D&spr=https&se=2022-11-25T16%3A24%3A35Z&sp=r",
    "image281086": "https://docserverpwaprodwus.blob.core.windows.net/85cb91a0-136e-43ce-b7be-ed7c25df8283-1/resource/Assets0Images00045.png?sv=2017-04-17&sr=b&sig=vpWD5f%2F9oWNAaP0fNtyAJLn9XSWv%2B1Wb0znEVkIERUM%3D&spr=https&se=2022-11-25T16%3A24%3A35Z&sp=r",
    "image281103": "https://docserverpwaprodwus.blob.core.windows.net/85cb91a0-136e-43ce-b7be-ed7c25df8283-1/resource/Assets0Images00046.png?sv=2017-04-17&sr=b&sig=ckRiP3XzziVhgcXwHav5FGG4EbDDEtQs%2FV6dVIBkcqE%3D&spr=https&se=2022-11-25T16%3A24%3A35Z&sp=r",
    "image281106": "https://docserverpwaprodwus.blob.core.windows.net/85cb91a0-136e-43ce-b7be-ed7c25df8283-1/resource/Assets0Images00047.png?sv=2017-04-17&sr=b&sig=eGbTw72GOrm8Q5aplZ6Ol%2BS80RZACa8Ei4WmwM2iDIA%3D&spr=https&se=2022-11-25T16%3A24%3A35Z&sp=r",
    "image28789": "https://docserverpwaprodwus.blob.core.windows.net/85cb91a0-136e-43ce-b7be-ed7c25df8283-1/resource/Assets0Images00048.png?sv=2017-04-17&sr=b&sig=o7g9id3S%2F5HDPufdjwPetDAWsHXkJSibqAfYSQZIyVg%3D&spr=https&se=2022-11-25T16%3A24%3A35Z&sp=r",
    "image28793": "https://docserverpwaprodwus.blob.core.windows.net/85cb91a0-136e-43ce-b7be-ed7c25df8283-1/resource/Assets0Images00049.png?sv=2017-04-17&sr=b&sig=SyMcyWbH5t78HDGcun%2BqaBfr48NTk3EMATEa7fPnY7Q%3D&spr=https&se=2022-11-25T16%3A24%3A35Z&sp=r",
    "image28828": "https://docserverpwaprodwus.blob.core.windows.net/85cb91a0-136e-43ce-b7be-ed7c25df8283-1/resource/Assets0Images00050.png?sv=2017-04-17&sr=b&sig=XaXyWNLIhEDXrBUQN5AEbqlQt%2BHw9v4GLTh%2FzbUirNM%3D&spr=https&se=2022-11-25T16%3A24%3A35Z&sp=r",
    "image28831": "https://docserverpwaprodwus.blob.core.windows.net/85cb91a0-136e-43ce-b7be-ed7c25df8283-1/resource/Assets0Images00051.png?sv=2017-04-17&sr=b&sig=TxP13Ymk28oA3OQ8hbAEx9dDsaVzmbQ96N6mUkpO1WA%3D&spr=https&se=2022-11-25T16%3A24%3A35Z&sp=r",
    "image28852": "https://docserverpwaprodwus.blob.core.windows.net/85cb91a0-136e-43ce-b7be-ed7c25df8283-1/resource/Assets0Images00052.png?sv=2017-04-17&sr=b&sig=YBbK1pdVOBPkKKEchWlP%2FfOm8iIxpnhszBJ21WSO4Is%3D&spr=https&se=2022-11-25T16%3A24%3A35Z&sp=r",
    "image28884": "https://docserverpwaprodwus.blob.core.windows.net/85cb91a0-136e-43ce-b7be-ed7c25df8283-1/resource/Assets0Images00053.png?sv=2017-04-17&sr=b&sig=TO%2BnVP8ZUIVvSU2xzrblbWx%2By6fq6M3XI0CzpMXEtCQ%3D&spr=https&se=2022-11-25T16%3A24%3A35Z&sp=r",
    "image28903": "https://docserverpwaprodwus.blob.core.windows.net/85cb91a0-136e-43ce-b7be-ed7c25df8283-1/resource/Assets0Images00054.png?sv=2017-04-17&sr=b&sig=VA6hWi5NnEiThEuskL%2BIyGW%2BnRrLLpr3fPpKmok0A70%3D&spr=https&se=2022-11-25T16%3A24%3A35Z&sp=r",
    "image28931": "https://docserverpwaprodwus.blob.core.windows.net/85cb91a0-136e-43ce-b7be-ed7c25df8283-1/resource/Assets0Images00055.png?sv=2017-04-17&sr=b&sig=Al%2BxSDjrZ4QNAuCKP9ukW4cimWC8QhmEI%2Fo3ZiOyVDo%3D&spr=https&se=2022-11-25T16%3A24%3A35Z&sp=r",
    "image28942": "https://docserverpwaprodwus.blob.core.windows.net/85cb91a0-136e-43ce-b7be-ed7c25df8283-1/resource/Assets0Images00056.png?sv=2017-04-17&sr=b&sig=PBmwCpHKRZmRfvofpyLSaL2PixKB4Ykux3EFDzK6iuw%3D&spr=https&se=2022-11-25T16%3A24%3A35Z&sp=r",
    "image28949": "https://docserverpwaprodwus.blob.core.windows.net/85cb91a0-136e-43ce-b7be-ed7c25df8283-1/resource/Assets0Images00057.png?sv=2017-04-17&sr=b&sig=%2FvCcBoJi99o%2FjaUKPwfkJB9njDSobbPaca%2Fd7p3fa50%3D&spr=https&se=2022-11-25T16%3A24%3A35Z&sp=r",
    "image28956": "https://docserverpwaprodwus.blob.core.windows.net/85cb91a0-136e-43ce-b7be-ed7c25df8283-1/resource/Assets0Images00058.png?sv=2017-04-17&sr=b&sig=3gf4rR4aymZQi1Oz%2B54%2BJpsyMeaRYk8LT9Hd26wg9hI%3D&spr=https&se=2022-11-25T16%3A24%3A35Z&sp=r",
    "image28963": "https://docserverpwaprodwus.blob.core.windows.net/85cb91a0-136e-43ce-b7be-ed7c25df8283-1/resource/Assets0Images00059.png?sv=2017-04-17&sr=b&sig=TMCATxclgRerDZD%2Bt4l24lVSUPDclf3W%2BQbTuKmIK48%3D&spr=https&se=2022-11-25T16%3A24%3A35Z&sp=r",
    "image28970": "https://docserverpwaprodwus.blob.core.windows.net/85cb91a0-136e-43ce-b7be-ed7c25df8283-1/resource/Assets0Images00060.png?sv=2017-04-17&sr=b&sig=%2FUrLop9mnnhlkFMoTJ7qR7uwh%2BPPzATSrWbyKG7LTJ0%3D&spr=https&se=2022-11-25T16%3A24%3A35Z&sp=r",
    "image28976": "https://docserverpwaprodwus.blob.core.windows.net/85cb91a0-136e-43ce-b7be-ed7c25df8283-1/resource/Assets0Images00061.png?sv=2017-04-17&sr=b&sig=UQc26UcGCIJn9WboTaOXCj0QRXgyYKuP8ojFUpby850%3D&spr=https&se=2022-11-25T16%3A24%3A35Z&sp=r",
    "image28981": "https://docserverpwaprodwus.blob.core.windows.net/85cb91a0-136e-43ce-b7be-ed7c25df8283-1/resource/Assets0Images00062.png?sv=2017-04-17&sr=b&sig=tItwqWrBkKbB%2BcG3vrarsSV5aNZ%2Bo4K6KVM%2Bswi%2BqWM%3D&spr=https&se=2022-11-25T16%3A24%3A35Z&sp=r",
    "image28995": "https://docserverpwaprodwus.blob.core.windows.net/85cb91a0-136e-43ce-b7be-ed7c25df8283-1/resource/Assets0Images00063.png?sv=2017-04-17&sr=b&sig=iyKSvYnbTXZukIOOG3j8pgb9qK%2B8gmI1MAXKpoU%2BWbQ%3D&spr=https&se=2022-11-25T16%3A24%3A35Z&sp=r",
    "image341155": "https://docserverpwaprodwus.blob.core.windows.net/85cb91a0-136e-43ce-b7be-ed7c25df8283-1/resource/Assets0Images00064.png?sv=2017-04-17&sr=b&sig=SfUHMeqmU0mgHQEB8dEgJ063NcOr9NBL30PUiMsJLrc%3D&spr=https&se=2022-11-25T16%3A24%3A35Z&sp=r",
    "image341169": "https://docserverpwaprodwus.blob.core.windows.net/85cb91a0-136e-43ce-b7be-ed7c25df8283-1/resource/Assets0Images00065.png?sv=2017-04-17&sr=b&sig=KJCWkLCQLGuo%2BdHeCwfc3tpej5fdML5fiXm%2F%2BE4OYNk%3D&spr=https&se=2022-11-25T16%3A24%3A35Z&sp=r",
    "image341191": "https://docserverpwaprodwus.blob.core.windows.net/85cb91a0-136e-43ce-b7be-ed7c25df8283-1/resource/Assets0Images00066.png?sv=2017-04-17&sr=b&sig=73jem1V3D%2FFPI29g29r0q%2FloxlqtAIirEe%2FOPemVNas%3D&spr=https&se=2022-11-25T16%3A24%3A35Z&sp=r",
    "image341196": "https://docserverpwaprodwus.blob.core.windows.net/85cb91a0-136e-43ce-b7be-ed7c25df8283-1/resource/Assets0Images00067.png?sv=2017-04-17&sr=b&sig=%2BJqX46F4yZ77Zz0rnDDb9swdWJzFtD5c4KYkiW%2Fojns%3D&spr=https&se=2022-11-25T16%3A24%3A35Z&sp=r",
    "image341202": "https://docserverpwaprodwus.blob.core.windows.net/85cb91a0-136e-43ce-b7be-ed7c25df8283-1/resource/Assets0Images00068.png?sv=2017-04-17&sr=b&sig=KzwAnpOVBkZLkEUjuJdBmXxxBVzkJYFP1I8dmMuEEDM%3D&spr=https&se=2022-11-25T16%3A24%3A35Z&sp=r",
    "image341207": "https://docserverpwaprodwus.blob.core.windows.net/85cb91a0-136e-43ce-b7be-ed7c25df8283-1/resource/Assets0Images00069.png?sv=2017-04-17&sr=b&sig=SLaDObaFWMK26GWmW9uv6SNxZ1TKoCBfMje%2B2AGdYJA%3D&spr=https&se=2022-11-25T16%3A24%3A35Z&sp=r",
    "image341222": "https://docserverpwaprodwus.blob.core.windows.net/85cb91a0-136e-43ce-b7be-ed7c25df8283-1/resource/Assets0Images00070.png?sv=2017-04-17&sr=b&sig=f2itYHkBPnezXOQeQp2iyPfGssSEpdtDmA3jeHlwRgo%3D&spr=https&se=2022-11-25T16%3A24%3A35Z&sp=r",
    "image341248": "https://docserverpwaprodwus.blob.core.windows.net/85cb91a0-136e-43ce-b7be-ed7c25df8283-1/resource/Assets0Images00071.png?sv=2017-04-17&sr=b&sig=0h6IQtnL3QzcdtoOIKnH%2BjJQ69ZlPqEo6hZn4Jt9QWA%3D&spr=https&se=2022-11-25T16%3A24%3A35Z&sp=r",
    "image341254": "https://docserverpwaprodwus.blob.core.windows.net/85cb91a0-136e-43ce-b7be-ed7c25df8283-1/resource/Assets0Images00072.png?sv=2017-04-17&sr=b&sig=GiEbiHATi7SDg1ljsU9qE8mQA1eH0zWgmAB3wqxCcDc%3D&spr=https&se=2022-11-25T16%3A24%3A35Z&sp=r",
    "image341256": "https://docserverpwaprodwus.blob.core.windows.net/85cb91a0-136e-43ce-b7be-ed7c25df8283-1/resource/Assets0Images00073.png?sv=2017-04-17&sr=b&sig=w%2BpuBKa4HBlJ1mMdDvps5AXfOE7KzFxl5CFKcsCdV2I%3D&spr=https&se=2022-11-25T16%3A24%3A35Z&sp=r",
    "image341264": "https://docserverpwaprodwus.blob.core.windows.net/85cb91a0-136e-43ce-b7be-ed7c25df8283-1/resource/Assets0Images00074.png?sv=2017-04-17&sr=b&sig=7RmEPDPvDA18hxwcUyNeaxQsA4aG80brMOzEKRY%2BMhY%3D&spr=https&se=2022-11-25T16%3A24%3A35Z&sp=r",
    "image341270": "https://docserverpwaprodwus.blob.core.windows.net/85cb91a0-136e-43ce-b7be-ed7c25df8283-1/resource/Assets0Images00075.png?sv=2017-04-17&sr=b&sig=UPagpH3FIQ2yWRihsbB4HHW00%2FLp7q4hy6yBudrSRHQ%3D&spr=https&se=2022-11-25T16%3A24%3A35Z&sp=r",
    "image341280": "https://docserverpwaprodwus.blob.core.windows.net/85cb91a0-136e-43ce-b7be-ed7c25df8283-1/resource/Assets0Images00076.png?sv=2017-04-17&sr=b&sig=QP6OTtp19QpD20aVA3qgp87i5lhjthj%2FoLrv9gBE0BM%3D&spr=https&se=2022-11-25T16%3A24%3A35Z&sp=r",
    "image341287": "https://docserverpwaprodwus.blob.core.windows.net/85cb91a0-136e-43ce-b7be-ed7c25df8283-1/resource/Assets0Images00077.png?sv=2017-04-17&sr=b&sig=c7csnMeevpwZ8yeskyeu9WnTDk4U8L7sFPQfP939st4%3D&spr=https&se=2022-11-25T16%3A24%3A35Z&sp=r",
    "image341294": "https://docserverpwaprodwus.blob.core.windows.net/85cb91a0-136e-43ce-b7be-ed7c25df8283-1/resource/Assets0Images00078.png?sv=2017-04-17&sr=b&sig=TfR4kOTFmUaiC5ZQ0ithNMmdeaafa%2ByolEffp7KUTd8%3D&spr=https&se=2022-11-25T16%3A24%3A35Z&sp=r",
    "image341301": "https://docserverpwaprodwus.blob.core.windows.net/85cb91a0-136e-43ce-b7be-ed7c25df8283-1/resource/Assets0Images00079.png?sv=2017-04-17&sr=b&sig=%2BUgH%2B8Xl4DnW2TMfCyssTUCKgPNN9%2F92%2BVadzpgBDOE%3D&spr=https&se=2022-11-25T16%3A24%3A35Z&sp=r",
    "image341308": "https://docserverpwaprodwus.blob.core.windows.net/85cb91a0-136e-43ce-b7be-ed7c25df8283-1/resource/Assets0Images00080.png?sv=2017-04-17&sr=b&sig=lpTe9DFeQjFDfZwKvkJLuXCLDITxAKv9UvCXShPNdNM%3D&spr=https&se=2022-11-25T16%3A24%3A35Z&sp=r",
    "image341314": "https://docserverpwaprodwus.blob.core.windows.net/85cb91a0-136e-43ce-b7be-ed7c25df8283-1/resource/Assets0Images00081.png?sv=2017-04-17&sr=b&sig=rYiVWCjIQLhInIwUmyROAo7rNXJ3Pty9ZCXudwvPvb8%3D&spr=https&se=2022-11-25T16%3A24%3A35Z&sp=r",
    "image341319": "https://docserverpwaprodwus.blob.core.windows.net/85cb91a0-136e-43ce-b7be-ed7c25df8283-1/resource/Assets0Images00082.png?sv=2017-04-17&sr=b&sig=%2Fy1Tul3qlGCiudGCnNhlWRBtRJqlWGJgq3QMagLyoc4%3D&spr=https&se=2022-11-25T16%3A24%3A35Z&sp=r",
    "image341345": "https://docserverpwaprodwus.blob.core.windows.net/85cb91a0-136e-43ce-b7be-ed7c25df8283-1/resource/Assets0Images00083.png?sv=2017-04-17&sr=b&sig=LeBMwApjftkG%2BLqs41w6LjNyQ7R6%2F9dumG%2FvTH%2BY8fI%3D&spr=https&se=2022-11-25T16%3A24%3A35Z&sp=r",
    "image341358": "https://docserverpwaprodwus.blob.core.windows.net/85cb91a0-136e-43ce-b7be-ed7c25df8283-1/resource/Assets0Images00084.png?sv=2017-04-17&sr=b&sig=qqV6OjUX%2BwwgE%2FoYNfaFSQLF0hoZ%2FNEmMAdmCz7Z8jA%3D&spr=https&se=2022-11-25T16%3A24%3A35Z&sp=r",
    "image341364": "https://docserverpwaprodwus.blob.core.windows.net/85cb91a0-136e-43ce-b7be-ed7c25df8283-1/resource/Assets0Images00085.png?sv=2017-04-17&sr=b&sig=bokxpxEOJq8z4lp0H21C%2FIUqIbwhE7NnPS9ryzBQnDE%3D&spr=https&se=2022-11-25T16%3A24%3A35Z&sp=r",
    "image341379": "https://docserverpwaprodwus.blob.core.windows.net/85cb91a0-136e-43ce-b7be-ed7c25df8283-1/resource/Assets0Images00086.png?sv=2017-04-17&sr=b&sig=56tHUgzNX9M0Y7pZ9bHhiEp9b9rhFzSCfSYXylv6Lpk%3D&spr=https&se=2022-11-25T16%3A24%3A35Z&sp=r",
    "image341381": "https://docserverpwaprodwus.blob.core.windows.net/85cb91a0-136e-43ce-b7be-ed7c25df8283-1/resource/Assets0Images00087.png?sv=2017-04-17&sr=b&sig=a56890F3yMdtljA8ZR3mVRnwfbPzHjWI6xjvKQtmZFM%3D&spr=https&se=2022-11-25T16%3A24%3A35Z&sp=r",
    "image361394": "https://docserverpwaprodwus.blob.core.windows.net/85cb91a0-136e-43ce-b7be-ed7c25df8283-1/resource/Assets0Images00088.png?sv=2017-04-17&sr=b&sig=csbCqWxo203v1YQ9Mb4I3ZGSTVKc9GW6NxPtr1dxzy0%3D&spr=https&se=2022-11-25T16%3A24%3A35Z&sp=r",
    "image361400": "https://docserverpwaprodwus.blob.core.windows.net/85cb91a0-136e-43ce-b7be-ed7c25df8283-1/resource/Assets0Images00089.png?sv=2017-04-17&sr=b&sig=E71cuCYIhrQs2bjsLnLZp73BPPSP43CEGxwCz%2BmfSqc%3D&spr=https&se=2022-11-25T16%3A24%3A35Z&sp=r",
    "image361401": "https://docserverpwaprodwus.blob.core.windows.net/85cb91a0-136e-43ce-b7be-ed7c25df8283-1/resource/Assets0Images00090.png?sv=2017-04-17&sr=b&sig=gz7R5nK6GaMxy6R9kuAklMp0SbkhNo5%2Ful9x%2F6imTK4%3D&spr=https&se=2022-11-25T16%3A24%3A35Z&sp=r",
    "image361402": "https://docserverpwaprodwus.blob.core.windows.net/85cb91a0-136e-43ce-b7be-ed7c25df8283-1/resource/Assets0Images00091.png?sv=2017-04-17&sr=b&sig=7PH%2FGcG8LWXVCg7U8Sx248mhyOxTSLxLHfmq0YuJ3dA%3D&spr=https&se=2022-11-25T16%3A24%3A35Z&sp=r",
    "image361403": "https://docserverpwaprodwus.blob.core.windows.net/85cb91a0-136e-43ce-b7be-ed7c25df8283-1/resource/Assets0Images00092.png?sv=2017-04-17&sr=b&sig=LaSgZETFCX02NzfbER%2FsTigQ6AwJMgu4HHvG29PUr30%3D&spr=https&se=2022-11-25T16%3A24%3A35Z&sp=r",
    "image361404": "https://docserverpwaprodwus.blob.core.windows.net/85cb91a0-136e-43ce-b7be-ed7c25df8283-1/resource/Assets0Images00093.png?sv=2017-04-17&sr=b&sig=w7hru%2Fo9AFtlBDX%2BsIRmYFyR8X%2FoVIdb%2FHoa%2FkMCBeA%3D&spr=https&se=2022-11-25T16%3A24%3A35Z&sp=r",
    "image361405": "https://docserverpwaprodwus.blob.core.windows.net/85cb91a0-136e-43ce-b7be-ed7c25df8283-1/resource/Assets0Images00094.png?sv=2017-04-17&sr=b&sig=0PPXexuEzvSwAkymHhd5Au1e84gRLfE5kCyQqxsFczc%3D&spr=https&se=2022-11-25T16%3A24%3A35Z&sp=r",
    "image361406": "https://docserverpwaprodwus.blob.core.windows.net/85cb91a0-136e-43ce-b7be-ed7c25df8283-1/resource/Assets0Images00095.png?sv=2017-04-17&sr=b&sig=2op%2BwGmjdBDmzWB4Ym7klNjk7sliCe2rXIZCcRWgVLo%3D&spr=https&se=2022-11-25T16%3A24%3A35Z&sp=r",
    "image361411": "https://docserverpwaprodwus.blob.core.windows.net/85cb91a0-136e-43ce-b7be-ed7c25df8283-1/resource/Assets0Images00096.png?sv=2017-04-17&sr=b&sig=jMuFIcKNiRLCcVC%2F5c67KL%2BjUfE8zR%2FE4fsFDv9xXLk%3D&spr=https&se=2022-11-25T16%3A24%3A35Z&sp=r",
    "image361479": "https://docserverpwaprodwus.blob.core.windows.net/85cb91a0-136e-43ce-b7be-ed7c25df8283-1/resource/Assets0Images00097.png?sv=2017-04-17&sr=b&sig=X90KIFPMQQuZvH7Fd11BWnUK4upHTHfUV3MeKUujBJo%3D&spr=https&se=2022-11-25T16%3A24%3A35Z&sp=r",
    "image361482": "https://docserverpwaprodwus.blob.core.windows.net/85cb91a0-136e-43ce-b7be-ed7c25df8283-1/resource/Assets0Images00098.png?sv=2017-04-17&sr=b&sig=fXba7%2BJGEFDrjAiASbIKlyWOeiJ2FKTEXM5lrPDCvlo%3D&spr=https&se=2022-11-25T16%3A24%3A35Z&sp=r",
    "image361485": "https://docserverpwaprodwus.blob.core.windows.net/85cb91a0-136e-43ce-b7be-ed7c25df8283-1/resource/Assets0Images00099.png?sv=2017-04-17&sr=b&sig=vWBwfTwxyC0CEEulxtnX%2BS4yoO%2BQiRdfZ8rdVumJ1Pg%3D&spr=https&se=2022-11-25T16%3A24%3A35Z&sp=r",
    "image371504": "https://docserverpwaprodwus.blob.core.windows.net/85cb91a0-136e-43ce-b7be-ed7c25df8283-1/resource/Assets0Images00100.png?sv=2017-04-17&sr=b&sig=w07jCa%2Bup5Q7WeMkj3NyMldDYwAgEsb6eOzD%2BIYIkdw%3D&spr=https&se=2022-11-25T16%3A24%3A35Z&sp=r",
    "image371506": "https://docserverpwaprodwus.blob.core.windows.net/85cb91a0-136e-43ce-b7be-ed7c25df8283-1/resource/Assets0Images00101.png?sv=2017-04-17&sr=b&sig=i%2BLgkhb8FOZI7mrTUhru1P4XaPeSv%2BTdvTXJnV9RPS4%3D&spr=https&se=2022-11-25T16%3A24%3A35Z&sp=r",
    "image371519": "https://docserverpwaprodwus.blob.core.windows.net/85cb91a0-136e-43ce-b7be-ed7c25df8283-1/resource/Assets0Images00102.png?sv=2017-04-17&sr=b&sig=No7o4ab5lJGvlLBFzsNMPbfKpqQ%2BFgPHHQ6etksEhnE%3D&spr=https&se=2022-11-25T16%3A24%3A35Z&sp=r",
    "image371572": "https://docserverpwaprodwus.blob.core.windows.net/85cb91a0-136e-43ce-b7be-ed7c25df8283-1/resource/Assets0Images00103.png?sv=2017-04-17&sr=b&sig=eUZYHc9D7rdydE%2FBE6h6Dit1fxQKTG1VTlK3dKeNdA8%3D&spr=https&se=2022-11-25T16%3A24%3A35Z&sp=r",
    "image371584": "https://docserverpwaprodwus.blob.core.windows.net/85cb91a0-136e-43ce-b7be-ed7c25df8283-1/resource/Assets0Images00104.png?sv=2017-04-17&sr=b&sig=Ties0o%2BiKVNL%2B%2Buau2vCsJhCe4%2BwThci0ecgYwPpJm8%3D&spr=https&se=2022-11-25T16%3A24%3A35Z&sp=r",
    "image371618": "https://docserverpwaprodwus.blob.core.windows.net/85cb91a0-136e-43ce-b7be-ed7c25df8283-1/resource/Assets0Images00105.png?sv=2017-04-17&sr=b&sig=WdykDraMGREfNGZMF8TC7rr6PEMxDqnUPjJasu6nSnQ%3D&spr=https&se=2022-11-25T16%3A24%3A35Z&sp=r",
    "image371637": "https://docserverpwaprodwus.blob.core.windows.net/85cb91a0-136e-43ce-b7be-ed7c25df8283-1/resource/Assets0Images00106.png?sv=2017-04-17&sr=b&sig=W9BTYXRshblvKXi7V2tzjc7j5JhseSlC74nOz4FiSP4%3D&spr=https&se=2022-11-25T16%3A24%3A35Z&sp=r",
    "image371646": "https://docserverpwaprodwus.blob.core.windows.net/85cb91a0-136e-43ce-b7be-ed7c25df8283-1/resource/Assets0Images00107.png?sv=2017-04-17&sr=b&sig=62yrZIqblVF25SP0ZhGNO%2BNwk3QD3jctRXBJ5Gojpyk%3D&spr=https&se=2022-11-25T16%3A24%3A35Z&sp=r",
    "image371662": "https://docserverpwaprodwus.blob.core.windows.net/85cb91a0-136e-43ce-b7be-ed7c25df8283-1/resource/Assets0Images00108.png?sv=2017-04-17&sr=b&sig=sGu73NbjlEzJKwKvRC%2BDOwU3Q1o0x4sEShpTfbZOOeA%3D&spr=https&se=2022-11-25T16%3A24%3A35Z&sp=r",
    "image371666": "https://docserverpwaprodwus.blob.core.windows.net/85cb91a0-136e-43ce-b7be-ed7c25df8283-1/resource/Assets0Images00109.png?sv=2017-04-17&sr=b&sig=xyX6EPA%2FnwwwDetesOiaxBVTDAtlKOcu94uVvOMPbzA%3D&spr=https&se=2022-11-25T16%3A24%3A35Z&sp=r",
    "image371667": "https://docserverpwaprodwus.blob.core.windows.net/85cb91a0-136e-43ce-b7be-ed7c25df8283-1/resource/Assets0Images00110.png?sv=2017-04-17&sr=b&sig=JMHytG%2FQXH35PSodSqM2Lgz2wknGcBwUY2ob9vXMIz8%3D&spr=https&se=2022-11-25T16%3A24%3A35Z&sp=r",
    "image371668": "https://docserverpwaprodwus.blob.core.windows.net/85cb91a0-136e-43ce-b7be-ed7c25df8283-1/resource/Assets0Images00111.png?sv=2017-04-17&sr=b&sig=FvUglRbtizaYuV09WGfaX0wQnDUYo4fBIhvo9frs7A8%3D&spr=https&se=2022-11-25T16%3A24%3A35Z&sp=r",
    "image371669": "https://docserverpwaprodwus.blob.core.windows.net/85cb91a0-136e-43ce-b7be-ed7c25df8283-1/resource/Assets0Images00112.png?sv=2017-04-17&sr=b&sig=sFm8JsOuUpC9Qjk9n5hFQOSRn1BYX%2FepermRlUIdQsA%3D&spr=https&se=2022-11-25T16%3A24%3A35Z&sp=r",
    "image381683": "https://docserverpwaprodwus.blob.core.windows.net/85cb91a0-136e-43ce-b7be-ed7c25df8283-1/resource/Assets0Images00113.png?sv=2017-04-17&sr=b&sig=vSSi3Tfu%2FI0JcJhgaAILd%2FRCGmW%2BRtrxWv1pv17ZjsU%3D&spr=https&se=2022-11-25T16%3A24%3A35Z&sp=r",
    "image381685": "https://docserverpwaprodwus.blob.core.windows.net/85cb91a0-136e-43ce-b7be-ed7c25df8283-1/resource/Assets0Images00114.png?sv=2017-04-17&sr=b&sig=n%2FcgwkbiZK5ye6pkAyGP9ljU%2F2wBMkGk9UFkpbC2Ze8%3D&spr=https&se=2022-11-25T16%3A24%3A35Z&sp=r",
    "image381693": "https://docserverpwaprodwus.blob.core.windows.net/85cb91a0-136e-43ce-b7be-ed7c25df8283-1/resource/Assets0Images00115.png?sv=2017-04-17&sr=b&sig=%2B9UgSy2wAj1W6uh227cLe1tVCax2Bm5WRQ9xLjyTsTY%3D&spr=https&se=2022-11-25T16%3A24%3A35Z&sp=r",
    "image381699": "https://docserverpwaprodwus.blob.core.windows.net/85cb91a0-136e-43ce-b7be-ed7c25df8283-1/resource/Assets0Images00116.png?sv=2017-04-17&sr=b&sig=zsNHOxKz0MVe9xhuAnPMs9lYWSW7QCINWDd6Grq1q8c%3D&spr=https&se=2022-11-25T16%3A24%3A35Z&sp=r",
    "image381701": "https://docserverpwaprodwus.blob.core.windows.net/85cb91a0-136e-43ce-b7be-ed7c25df8283-1/resource/Assets0Images00117.png?sv=2017-04-17&sr=b&sig=DpM2UD5fD4Sw2e7aBARX%2FpV2aCWzHfN86DPh%2Fzk0amA%3D&spr=https&se=2022-11-25T16%3A24%3A35Z&sp=r",
    "image381709": "https://docserverpwaprodwus.blob.core.windows.net/85cb91a0-136e-43ce-b7be-ed7c25df8283-1/resource/Assets0Images00118.png?sv=2017-04-17&sr=b&sig=9jSW5rYiusNJdY7MsWr1I%2FhdJSWtCEZRWFqtwfQJNFU%3D&spr=https&se=2022-11-25T16%3A24%3A35Z&sp=r",
    "image381715": "https://docserverpwaprodwus.blob.core.windows.net/85cb91a0-136e-43ce-b7be-ed7c25df8283-1/resource/Assets0Images00119.png?sv=2017-04-17&sr=b&sig=s41k3vfLNsxOMZz3gH8gGLjUOQf%2BjHA%2FDgJObqaIp0Y%3D&spr=https&se=2022-11-25T16%3A24%3A35Z&sp=r",
    "image381718": "https://docserverpwaprodwus.blob.core.windows.net/85cb91a0-136e-43ce-b7be-ed7c25df8283-1/resource/Assets0Images00120.png?sv=2017-04-17&sr=b&sig=uVnD5z5j6yPTvRUc9n1euSddOtMkTvqCSV5rUYRM9l8%3D&spr=https&se=2022-11-25T16%3A24%3A35Z&sp=r",
    "image381731": "https://docserverpwaprodwus.blob.core.windows.net/85cb91a0-136e-43ce-b7be-ed7c25df8283-1/resource/Assets0Images00121.png?sv=2017-04-17&sr=b&sig=un9St1cgGQAOcXClwOvXXK0junIU5eYpI8JPQaKJncU%3D&spr=https&se=2022-11-25T16%3A24%3A35Z&sp=r",
    "image381733": "https://docserverpwaprodwus.blob.core.windows.net/85cb91a0-136e-43ce-b7be-ed7c25df8283-1/resource/Assets0Images00122.png?sv=2017-04-17&sr=b&sig=%2B%2Bh3YvKQbpJvpUyu%2F6wkBhIxJ8ORKfMvTYNeV03DXwI%3D&spr=https&se=2022-11-25T16%3A24%3A35Z&sp=r",
    "image381737": "https://docserverpwaprodwus.blob.core.windows.net/85cb91a0-136e-43ce-b7be-ed7c25df8283-1/resource/Assets0Images00123.png?sv=2017-04-17&sr=b&sig=hxA2jGUYdRlTcXf9vwuvfqy%2BNQcWq2542d8nK0WAIyo%3D&spr=https&se=2022-11-25T16%3A24%3A35Z&sp=r",
    "image381746": "https://docserverpwaprodwus.blob.core.windows.net/85cb91a0-136e-43ce-b7be-ed7c25df8283-1/resource/Assets0Images00124.png?sv=2017-04-17&sr=b&sig=%2BAi8%2BIJ7laG7ws3ouqHh5fuBxrmKDl6KZbxcYm%2B6UJ4%3D&spr=https&se=2022-11-25T16%3A24%3A35Z&sp=r",
    "image381768": "https://docserverpwaprodwus.blob.core.windows.net/85cb91a0-136e-43ce-b7be-ed7c25df8283-1/resource/Assets0Images00125.png?sv=2017-04-17&sr=b&sig=RMdtQc4A4u6fY8E%2Frn2m3rRGDHaod9kriYYw4ydlKrA%3D&spr=https&se=2022-11-25T16%3A24%3A35Z&sp=r",
    "image381773": "https://docserverpwaprodwus.blob.core.windows.net/85cb91a0-136e-43ce-b7be-ed7c25df8283-1/resource/Assets0Images00126.png?sv=2017-04-17&sr=b&sig=0Ullm%2FpXIVviloMrFqoW1be27yBCLRJ2loVkd4uNLME%3D&spr=https&se=2022-11-25T16%3A24%3A35Z&sp=r",
    "image381784": "https://docserverpwaprodwus.blob.core.windows.net/85cb91a0-136e-43ce-b7be-ed7c25df8283-1/resource/Assets0Images00127.png?sv=2017-04-17&sr=b&sig=q%2FxxP6FjX058mSFrjB2JE9FTXXmVNvyFF5rbYg0vsoY%3D&spr=https&se=2022-11-25T16%3A24%3A35Z&sp=r",
    "image381789": "https://docserverpwaprodwus.blob.core.windows.net/85cb91a0-136e-43ce-b7be-ed7c25df8283-1/resource/Assets0Images00128.png?sv=2017-04-17&sr=b&sig=yroshfVkFQ04zRwl%2Bsryza85X%2BdYj7q4GAvvIe4aldI%3D&spr=https&se=2022-11-25T16%3A24%3A35Z&sp=r",
    "image381793": "https://docserverpwaprodwus.blob.core.windows.net/85cb91a0-136e-43ce-b7be-ed7c25df8283-1/resource/Assets0Images00129.png?sv=2017-04-17&sr=b&sig=qwP9eZHlEE64m1yRsZ1xUT01WvcBbG9LdMZa7oh4QD8%3D&spr=https&se=2022-11-25T16%3A24%3A35Z&sp=r",
    "image381796": "https://docserverpwaprodwus.blob.core.windows.net/85cb91a0-136e-43ce-b7be-ed7c25df8283-1/resource/Assets0Images00130.png?sv=2017-04-17&sr=b&sig=kens7pFfCVIIvC%2BADPki%2B6L0vTy5mnCcg%2B9%2B1%2B0igCU%3D&spr=https&se=2022-11-25T16%3A24%3A35Z&sp=r",
    "image381850": "https://docserverpwaprodwus.blob.core.windows.net/85cb91a0-136e-43ce-b7be-ed7c25df8283-1/resource/Assets0Images00131.png?sv=2017-04-17&sr=b&sig=uP3Q3P%2FTHXhb%2B8HuGfZqi9zr2Ijwx4ZTDHTt2RNyyrE%3D&spr=https&se=2022-11-25T16%3A24%3A35Z&sp=r",
    "image381863": "https://docserverpwaprodwus.blob.core.windows.net/85cb91a0-136e-43ce-b7be-ed7c25df8283-1/resource/Assets0Images00132.png?sv=2017-04-17&sr=b&sig=yytH1X%2BLXpLHu1SajY5A8ckNPDnk0dPGWvURc6TP6l0%3D&spr=https&se=2022-11-25T16%3A24%3A35Z&sp=r",
    "image381870": "https://docserverpwaprodwus.blob.core.windows.net/85cb91a0-136e-43ce-b7be-ed7c25df8283-1/resource/Assets0Images00133.png?sv=2017-04-17&sr=b&sig=XVpWZPcPRICsOwFTzXEtuC5z5D22hcjyCV1RtyWhU84%3D&spr=https&se=2022-11-25T16%3A24%3A35Z&sp=r",
    "image381875": "https://docserverpwaprodwus.blob.core.windows.net/85cb91a0-136e-43ce-b7be-ed7c25df8283-1/resource/Assets0Images00134.png?sv=2017-04-17&sr=b&sig=IPKtAPiAVtaciF6kn0qkZU1I7Zegw8FrxYG5%2F21V22Y%3D&spr=https&se=2022-11-25T16%3A24%3A35Z&sp=r",
    "image582108": "https://docserverpwaprodwus.blob.core.windows.net/85cb91a0-136e-43ce-b7be-ed7c25df8283-1/resource/Assets0Images00135.png?sv=2017-04-17&sr=b&sig=s7eUAab%2FtHfDIF%2Ft2kl9gCjCF9ctq54vCtnSCNft3jo%3D&spr=https&se=2022-11-25T16%3A24%3A35Z&sp=r",
    "image582167": "https://docserverpwaprodwus.blob.core.windows.net/85cb91a0-136e-43ce-b7be-ed7c25df8283-1/resource/Assets0Images00136.png?sv=2017-04-17&sr=b&sig=7fuesy9N1RKnhggREN7EYrRA5iPUKk6%2F1oiew2cm5W4%3D&spr=https&se=2022-11-25T16%3A24%3A35Z&sp=r",
    "image8150": "https://docserverpwaprodwus.blob.core.windows.net/85cb91a0-136e-43ce-b7be-ed7c25df8283-1/resource/Assets0Images00137.png?sv=2017-04-17&sr=b&sig=Lm3O7h9f3P%2F3%2FIk4bGdLszEX%2BAA34kDcs3TRBeWbzbs%3D&spr=https&se=2022-11-25T16%3A24%3A35Z&sp=r",
    "time-is-money-sandglass-investment-countdown-measure-concept": "https://docserverpwaprodwus.blob.core.windows.net/85cb91a0-136e-43ce-b7be-ed7c25df8283-1/resource/Assets0Images00138.jpg?sv=2017-04-17&sr=b&sig=hlxw%2B603o%2F0f3IIiheFwNYnrEnm7U%2Fsr1H2yHg%2BFNLE%3D&spr=https&se=2022-11-25T16%3A24%3A35Z&sp=r"
  },
  "OldLogoFileName": "logo.jpg",
  "OrderComponentMetadata": {
    "347fbc906fcc4827a384a06fc53242d5": 6,
    "3b02a9f7681e4ebe8a0ed199a55799c5": 0,
    "621de0cc4b9444b2909c35573e5077f6": 1,
    "8fcf01ef466b4b9e8b209f504771e604": 3,
    "956fd0c79bbe4571aaae7899200e6c6c": 8,
    "9a83575689f34468870fdfb0440f83df": 4,
    "a7e4976df95341fea6b6fdca9e07ac48": 2,
    "e9a328c0cd914fc998633dc57e7f1201": 7,
    "faecc12050bb4c9ca744ac80084ea13a": 5
  },
  "OrderComponentTemplate": {
    "347fbc906fcc4827a384a06fc53242d5": 6,
    "3b02a9f7681e4ebe8a0ed199a55799c5": 0,
    "621de0cc4b9444b2909c35573e5077f6": 1,
    "8fcf01ef466b4b9e8b209f504771e604": 3,
    "956fd0c79bbe4571aaae7899200e6c6c": 8,
    "9a83575689f34468870fdfb0440f83df": 4,
    "a7e4976df95341fea6b6fdca9e07ac48": 2,
    "e9a328c0cd914fc998633dc57e7f1201": 7,
    "faecc12050bb4c9ca744ac80084ea13a": 5
  },
  "OrderDataSource": {
    "ComboBoxSample": 1,
    "CustomGallerySample": 2,
    "Documentos": 3,
    "DropDownSample": 4,
    "ListboxSample": 5,
    "Send_an_email_invite": 0,
    "tbl_collaborators": 6,
    "tbl_companies": 7,
    "tbl_contract_projects": 9,
    "tbl_contracts": 8,
    "tbl_projects": 10,
    "tbl_projects_tasks": 11,
    "tbl_tasks": 12
  },
  "OrderGroupControls": {
    "Group1": {
      "Label20323": 1,
      "Rectangle20322": 0
    },
    "Group1_1": {
      "Label20323_1": 1,
      "Rectangle20322_2": 0
    },
    "Group2_1": {
      "Image341287_1": 1,
      "Image341294_1": 5,
      "Image341301_1": 9,
      "Image341308_1": 13,
      "Image341319_1": 19,
      "Label341289_1": 3,
      "Label341296_1": 7,
      "Label341303_1": 11,
      "Label341310_1": 15,
      "Label341315_1": 17,
      "Label341320_1": 20,
      "Rectangle341285_1": 0,
      "Rectangle341288_1": 2,
      "Rectangle341292_1": 4,
      "Rectangle341295_1": 6,
      "Rectangle341299_1": 8,
      "Rectangle341302_1": 10,
      "Rectangle341306_1": 12,
      "Rectangle341309_1": 14,
      "Rectangle341311_1": 16,
      "Rectangle341317_1": 18
    },
    "Group3": {
      "Gallery3": 0,
      "inputSearchProjectByName": 1
    },
    "Group7": {
      "Image28949": 1,
      "Image28956": 5,
      "Image28963": 9,
      "Image28970": 13,
      "Image28981": 19,
      "Label28951": 3,
      "Label28958": 7,
      "Label28965": 11,
      "Label28972": 15,
      "Label28977": 17,
      "Label28982": 20,
      "Rectangle28947": 0,
      "Rectangle28950": 2,
      "Rectangle28954": 4,
      "Rectangle28957": 6,
      "Rectangle28961": 8,
      "Rectangle28964": 10,
      "Rectangle28968": 12,
      "Rectangle28971": 14,
      "Rectangle28973": 16,
      "Rectangle28979": 18
    },
    "HoursProjectCard": {
      "Rectangle20322_1": 0,
      "TotalHoursProject": 1
    },
    "IconBack": {
      "Icon7": 0,
      "Icon7_1": 1
    },
    "IconBack_1": {
      "Icon7_2": 0,
      "Icon7_3": 1
    }
  },
  "OrderPcfTemplate": {},
  "OrderTemplate": {},
  "OrderXMLTemplate": {
    "button": 5,
    "circle": 12,
    "combobox": 9,
    "datepicker": 11,
    "dropdown": 7,
    "form": 3,
    "formViewer": 15,
    "gallery": 10,
    "groupContainer": 8,
    "icon": 1,
    "image": 6,
    "label": 2,
    "rectangle": 0,
    "text": 4,
    "timer": 14,
    "toggleSwitch": 13
  },
  "PublishOrderIndices": {
    "Alterar_Projeto_empresa": 45,
    "App": 0,
    "AppTittle": 8,
    "Atividade_alterada_colaborador": 64,
    "Atividade_criada_colaborador": 70,
    "atualizar_dados_empresa": 76,
    "BackgroundFooterDark": 547,
    "BackgroundFooterLight": 545,
    "BackgroundHeaderDark": 549,
    "BackgroundHeaderDark_2": 553,
    "BackImage": 2,
    "Body1": 190,
    "Body3": 386,
    "BodyToEmailTextInput": 529,
    "Buscar_por_colaboradores_empresa": 104,
    "Buscar_por_projeto_empresa": 117,
    "Button1": 564,
    "Button2": 531,
    "Button4": 565,
    "ButtonActivitiesWorker": 327,
    "ButtonBack": 195,
    "ButtonBack_1": 135,
    "ButtonBack_3": 155,
    "ButtonBack_4": 459,
    "ButtonBack_5": 495,
    "ButtonCreateActivityWorker": 326,
    "ButtonCreateProjectCompany": 90,
    "ButtonCreateProjectWorker": 331,
    "ButtonCreateUserCompany": 42,
    "ButtonCreateUserWorker": 76,
    "ButtonDirectWorker": 93,
    "ButtonDisable_1": 225,
    "ButtonDisable_2": 156,
    "ButtonDisable_3": 460,
    "ButtonDisable_4": 496,
    "ButtonDownload": 196,
    "ButtonDownload_1": 136,
    "ButtonDownload_2": 392,
    "ButtonEditActivity": 425,
    "ButtonEditProject": 124,
    "ButtonEditUserCompany": 89,
    "ButtonEditUserWorker": 330,
    "ButtonHome_1": 107,
    "ButtonHome_2": 162,
    "ButtonHome_3": 174,
    "ButtonHome_4": 231,
    "ButtonHome_6": 323,
    "ButtonHome_7": 312,
    "ButtonHome_8": 224,
    "ButtonHome_9": 270,
    "ButtonHomeWorker_10": 518,
    "ButtonHomeWorker_3": 367,
    "ButtonHomeWorker_4": 373,
    "ButtonHomeWorker_5": 391,
    "ButtonHomeWorker_6": 424,
    "ButtonHomeWorker_7": 501,
    "ButtonHomeWorker_8": 465,
    "ButtonHomeWorker_9": 523,
    "ButtonLogin": 16,
    "ButtonProjects": 85,
    "ButtonRegistration": 15,
    "ButtonRegistration_1": 47,
    "ButtonRegistration_2": 81,
    "ButtonSave_1": 226,
    "ButtonSave_2": 157,
    "ButtonSave_3": 271,
    "ButtonSave_4": 313,
    "ButtonSave_5": 461,
    "ButtonSave_6": 497,
    "ButtonSaveWorker_1": 368,
    "ButtonSaveWorker_2": 519,
    "ButtonWorkers": 86,
    "cadastro_colaborador": 130,
    "cadastro_empresa": 159,
    "cmpLoginFail": 1,
    "cmpLoginFail_1": 3,
    "cmpScreenSuccess": 7,
    "cmpScreenSuccess_1": 6,
    "cmpTransitionLoad": 12,
    "cmpTransitionLoadLogin": 5,
    "cnpj_DataCard1": 22,
    "cnpj_DataCard1_1": 204,
    "cnpj_DataCard2": 401,
    "Colaborador": 180,
    "colaborador_alocado_empresa": 184,
    "ComboBox1": 282,
    "Conta_Alterada_colaborador": 191,
    "Conta_Alterada_empresa": 197,
    "Conta_criada_colaborador": 204,
    "Conta_criada_empresa": 211,
    "Container1": 560,
    "cpf_DataCard2": 51,
    "cpf_DataCard2_1": 470,
    "criar_Projeto_colaborador": 218,
    "criar_Projeto_empresa": 237,
    "DataCardKey10": 113,
    "DataCardKey11": 116,
    "DataCardKey12": 119,
    "DataCardKey13": 146,
    "DataCardKey13_1": 240,
    "DataCardKey13_2": 507,
    "DataCardKey15": 73,
    "DataCardKey15_1": 492,
    "DataCardKey16": 151,
    "DataCardKey16_1": 245,
    "DataCardKey16_2": 512,
    "DataCardKey17": 344,
    "DataCardKey17_1": 436,
    "DataCardKey18": 349,
    "DataCardKey18_1": 441,
    "DataCardKey19": 354,
    "DataCardKey19_1": 446,
    "DataCardKey2": 23,
    "DataCardKey2_1": 205,
    "DataCardKey20": 359,
    "DataCardKey20_1": 451,
    "DataCardKey21": 364,
    "DataCardKey21_1": 456,
    "DataCardKey22_1": 281,
    "DataCardKey23": 122,
    "DataCardKey27": 410,
    "DataCardKey28": 413,
    "DataCardKey29": 416,
    "DataCardKey3": 28,
    "DataCardKey3_1": 210,
    "DataCardKey30": 419,
    "DataCardKey31": 422,
    "DataCardKey4": 33,
    "DataCardKey4_1": 215,
    "DataCardKey5": 52,
    "DataCardKey5_1": 471,
    "DataCardKey56": 402,
    "DataCardKey57": 399,
    "DataCardKey58": 405,
    "DataCardKey6": 58,
    "DataCardKey6_1": 477,
    "DataCardKey7": 38,
    "DataCardKey7_1": 220,
    "DataCardKey8": 63,
    "DataCardKey8_1": 482,
    "DataCardKey9": 68,
    "DataCardKey9_1": 487,
    "DataCardValue10": 117,
    "DataCardValue11": 120,
    "DataCardValue12": 69,
    "DataCardValue12_1": 488,
    "DataCardValue14": 148,
    "DataCardValue14_1": 242,
    "DataCardValue14_2": 509,
    "DataCardValue15": 74,
    "DataCardValue15_1": 493,
    "DataCardValue16": 153,
    "DataCardValue16_1": 247,
    "DataCardValue16_2": 514,
    "DataCardValue17": 345,
    "DataCardValue17_1": 437,
    "DataCardValue18": 350,
    "DataCardValue18_1": 442,
    "DataCardValue19": 355,
    "DataCardValue19_1": 447,
    "DataCardValue2": 25,
    "DataCardValue2_1": 207,
    "DataCardValue20": 360,
    "DataCardValue20_1": 452,
    "DataCardValue21": 365,
    "DataCardValue21_1": 457,
    "DataCardValue23": 123,
    "DataCardValue27": 411,
    "DataCardValue28": 414,
    "DataCardValue29": 417,
    "DataCardValue3": 30,
    "DataCardValue3_1": 212,
    "DataCardValue30": 420,
    "DataCardValue31": 423,
    "DataCardValue4": 35,
    "DataCardValue4_1": 217,
    "DataCardValue5": 54,
    "DataCardValue5_1": 473,
    "DataCardValue56": 403,
    "DataCardValue57": 400,
    "DataCardValue58": 406,
    "DataCardValue6": 59,
    "DataCardValue6_1": 478,
    "DataCardValue7": 40,
    "DataCardValue7_1": 222,
    "DataCardValue8": 64,
    "DataCardValue8_1": 483,
    "DataCardValue9": 114,
    "DataTable2": 315,
    "date_DataCard1": 357,
    "date_DataCard1_1": 449,
    "date_DataCard3": 418,
    "description_DataCard1": 347,
    "description_DataCard1_1": 439,
    "description_DataCard3": 412,
    "Designar_colaborador_empresa": 278,
    "DropdownCompany": 338,
    "DropdownCompany_1": 430,
    "DropdownCompany_2": 517,
    "DropdownCompany_3": 378,
    "DropdownMonth": 184,
    "DropdownMonth_1": 380,
    "DropdownProject": 340,
    "DropdownProject_1": 432,
    "editar_atividade_colaborador_1": 336,
    "editar_cadastro_colaborador": 372,
    "email_DataCard1": 404,
    "email_DataCard2": 32,
    "email_DataCard2_1": 214,
    "email_DataCard3": 66,
    "email_DataCard3_1": 485,
    "ErrorMessage13": 149,
    "ErrorMessage13_1": 243,
    "ErrorMessage13_2": 510,
    "ErrorMessage15": 75,
    "ErrorMessage15_1": 494,
    "ErrorMessage16": 154,
    "ErrorMessage16_1": 248,
    "ErrorMessage16_2": 515,
    "ErrorMessage17": 346,
    "ErrorMessage17_1": 438,
    "ErrorMessage18": 351,
    "ErrorMessage18_1": 443,
    "ErrorMessage19": 356,
    "ErrorMessage19_1": 448,
    "ErrorMessage2": 26,
    "ErrorMessage2_1": 208,
    "ErrorMessage20": 361,
    "ErrorMessage20_1": 453,
    "ErrorMessage21": 366,
    "ErrorMessage21_1": 458,
    "ErrorMessage3": 31,
    "ErrorMessage3_1": 213,
    "ErrorMessage4": 36,
    "ErrorMessage4_1": 218,
    "ErrorMessage5": 55,
    "ErrorMessage5_1": 474,
    "ErrorMessage6": 60,
    "ErrorMessage6_1": 479,
    "ErrorMessage7": 41,
    "ErrorMessage7_1": 223,
    "ErrorMessage8": 65,
    "ErrorMessage8_1": 484,
    "ErrorMessage9": 70,
    "ErrorMessage9_1": 489,
    "FooterCompany": 17,
    "FooterCompany_1": 96,
    "FooterCompany_10": 158,
    "FooterCompany_11": 273,
    "FooterCompany_12": 227,
    "FooterCompany_13": 176,
    "FooterCompany_14": 109,
    "FooterCompany_15": 43,
    "FooterCompany_2": 200,
    "FooterCompany_3": 141,
    "FooterCompany_4": 233,
    "FooterCompany_5": 49,
    "FooterCompany_6": 164,
    "FooterCompany_7": 277,
    "FooterCompany_8": 325,
    "FooterCompany_9": 319,
    "FooterWorker": 20,
    "FooterWorker_1": 335,
    "FooterWorker_10": 427,
    "FooterWorker_11": 462,
    "FooterWorker_12": 498,
    "FooterWorker_13": 521,
    "FooterWorker_2": 503,
    "FooterWorker_3": 467,
    "FooterWorker_4": 83,
    "FooterWorker_5": 375,
    "FooterWorker_6": 525,
    "FooterWorker_7": 77,
    "FooterWorker_8": 370,
    "FooterWorker_9": 395,
    "FormActivity": 341,
    "FormActivity_1": 433,
    "FormCompanyReg": 21,
    "FormCompanyReg_1": 203,
    "FormProjectCreate_1": 238,
    "FormProjectCreate_2": 505,
    "FormProjectEdit": 144,
    "FormViewerCompany": 397,
    "FormViewerProject1": 111,
    "FormViewerTasks": 408,
    "FormWorkerEdit": 469,
    "FormWorkerReg": 50,
    "Gallery2": 185,
    "Gallery3": 285,
    "Gallery5": 125,
    "Gallery7": 381,
    "GalleryCollaborators": 169,
    "GalleryProject": 101,
    "galleryTemplate1": 102,
    "galleryTemplate2": 170,
    "galleryTemplate4": 186,
    "galleryTemplate5": 286,
    "galleryTemplate7": 126,
    "galleryTemplate9": 382,
    "Group": 546,
    "Group_1": 548,
    "Group1": 178,
    "Group1_1": 376,
    "Group2_1": 236,
    "Group3": 284,
    "Group7": 291,
    "HeaderCompany": 23,
    "HeaderCompany_1": 84,
    "HeaderCompany_10": 234,
    "HeaderCompany_11": 201,
    "HeaderCompany_12": 165,
    "HeaderCompany_13": 97,
    "HeaderCompany_14": 44,
    "HeaderCompany_2": 177,
    "HeaderCompany_3": 110,
    "HeaderCompany_4": 228,
    "HeaderCompany_5": 159,
    "HeaderCompany_6": 274,
    "HeaderCompany_7": 320,
    "HeaderCompany_8": 278,
    "HeaderCompany_9": 142,
    "HeaderCompany_cad_empresa": 20,
    "HeaderCompany_cad_empresa_1": 279,
    "HeaderWorker": 28,
    "Horas_por_Colaborador_empresa": 404,
    "hours_DataCard1": 362,
    "hours_DataCard1_1": 454,
    "hours_DataCard3": 421,
    "HoursProjectCard": 133,
    "Icon19": 48,
    "Icon19_1": 82,
    "Icon19_10": 314,
    "Icon19_11": 272,
    "Icon19_12": 393,
    "Icon19_13": 426,
    "Icon19_14": 502,
    "Icon19_15": 466,
    "Icon19_16": 524,
    "Icon19_17": 520,
    "Icon19_2": 369,
    "Icon19_3": 108,
    "Icon19_4": 163,
    "Icon19_5": 232,
    "Icon19_6": 276,
    "Icon19_7": 175,
    "Icon19_8": 324,
    "Icon19_9": 374,
    "Icon2": 530,
    "Icon7": 199,
    "Icon7_1": 198,
    "Icon7_2": 140,
    "Icon7_3": 138,
    "IconActivities": 329,
    "IconAddActivity": 328,
    "IconAddProject": 333,
    "IconAddProjectCompany": 92,
    "IconBack": 179,
    "IconBack_1": 139,
    "iconCheck1_4": 539,
    "iconCircle1_4": 538,
    "iconCircleIcon": 534,
    "IconDirectWorker": 94,
    "IconDownload": 197,
    "IconDownload_1": 137,
    "IconDownload_2": 394,
    "IconLeft": 550,
    "IconLeft_2": 554,
    "iconMidlleScreen": 535,
    "IconProjects": 87,
    "IconRight": 552,
    "IconRight_2": 556,
    "IconSearch1": 100,
    "IconSearch1_1": 168,
    "IconUserCompany": 91,
    "IconUserWorker": 332,
    "IconWorkers": 88,
    "Image1": 543,
    "Image2": 334,
    "Image28949": 311,
    "Image28956": 307,
    "Image28963": 303,
    "Image28970": 299,
    "Image28981": 295,
    "Image341256": 371,
    "Image341287_1": 269,
    "Image341294_1": 265,
    "Image341301_1": 261,
    "Image341308_1": 257,
    "Image341319_1": 253,
    "Image341381": 229,
    "Image341381_1": 499,
    "Image371666": 275,
    "Image371666_1": 522,
    "Image371667": 321,
    "Image371668": 160,
    "Image371669": 463,
    "Image381685": 45,
    "Image381685_1": 79,
    "Image381796": 95,
    "ImgLoadLogin_1": 1,
    "infCont": 558,
    "inicial_colaborador": 429,
    "inicial_empresa": 440,
    "inputSearchProjectByName": 283,
    "inserir_atividade_colaborador": 454,
    "Label1": 7,
    "Label2": 14,
    "Label20323": 194,
    "Label20323_1": 390,
    "Label20324": 193,
    "Label20324_1": 389,
    "Label20480": 182,
    "Label20480_1": 181,
    "Label281068": 322,
    "Label281087_6": 559,
    "Label28951": 310,
    "Label28958": 306,
    "Label28965": 302,
    "Label28972": 298,
    "Label28977": 294,
    "Label28982": 290,
    "Label3": 561,
    "Label341255": 372,
    "Label341271": 464,
    "Label341289_1": 268,
    "Label341296_1": 264,
    "Label341303_1": 260,
    "Label341310_1": 256,
    "Label341315_1": 252,
    "Label341320_1": 249,
    "Label341365": 161,
    "Label341380": 230,
    "Label341380_1": 500,
    "Label381684": 46,
    "Label381684_1": 80,
    "Label5": 563,
    "LabelCompanyName": 337,
    "LabelCompanyName_1": 429,
    "LabelCompanyName_2": 516,
    "LabelLoginError": 11,
    "LabelPasswordError": 13,
    "LabelProjectName": 339,
    "LabelProjectName_1": 431,
    "LabelProjectName_2": 407,
    "lblLoadingMsgMiddleScreen": 544,
    "LblSuccessMsg1_4": 540,
    "lblSuccessMsgMiddleScreen": 536,
    "login": 490,
    "mainContainer": 532,
    "mainContainer_1": 541,
    "manager_Column1": 317,
    "manager_DataCard1": 150,
    "manager_DataCard1_1": 244,
    "manager_DataCard1_2": 511,
    "manager_DataCard2": 115,
    "modalSuccess": 557,
    "MonthLabel": 183,
    "MonthLabel_1": 379,
    "name_Column1": 316,
    "name_DataCard1": 112,
    "name_DataCard2": 27,
    "name_DataCard2_1": 209,
    "name_DataCard3": 56,
    "name_DataCard3_1": 475,
    "name_DataCard4": 145,
    "name_DataCard4_1": 239,
    "name_DataCard4_2": 506,
    "name_DataCard5": 342,
    "name_DataCard5_1": 434,
    "name_DataCard6": 409,
    "name_DataCard7": 398,
    "NameLogin_2": 551,
    "NameLogin_3": 555,
    "NextArrow1": 104,
    "NextArrow12": 385,
    "NextArrow4": 189,
    "NextArrow5": 171,
    "NextArrow8": 128,
    "NextArrow8_1": 288,
    "password_DataCard1": 37,
    "password_DataCard1_1": 219,
    "password_DataCard2": 71,
    "password_DataCard2_1": 490,
    "ProjectsLabel": 98,
    "ProjectsLabel_1": 166,
    "Projeto_alterado_empresa": 509,
    "Projeto_criado_colaborador": 516,
    "Projeto_criado_empresa": 521,
    "rect": 4,
    "Rectangle1": 566,
    "Rectangle20308_4": 78,
    "Rectangle20322": 192,
    "Rectangle20322_1": 132,
    "Rectangle20322_2": 388,
    "Rectangle28947": 309,
    "Rectangle28950": 308,
    "Rectangle28954": 305,
    "Rectangle28957": 304,
    "Rectangle28961": 301,
    "Rectangle28964": 300,
    "Rectangle28968": 297,
    "Rectangle28971": 296,
    "Rectangle28973": 292,
    "Rectangle28979": 293,
    "Rectangle3_4": 537,
    "Rectangle341285_1": 267,
    "Rectangle341288_1": 266,
    "Rectangle341292_1": 263,
    "Rectangle341295_1": 262,
    "Rectangle341299_1": 259,
    "Rectangle341302_1": 258,
    "Rectangle341306_1": 255,
    "Rectangle341309_1": 254,
    "Rectangle341311_1": 250,
    "Rectangle341317_1": 251,
    "rectContainer": 533,
    "rectContainer_1": 542,
    "Scr_teste_envio_email": 526,
    "SearchBox": 99,
    "SearchBox_1": 167,
    "SendFromEmailTextInput": 526,
    "SendToEmailTextInput": 527,
    "Separator1": 106,
    "Separator12": 387,
    "Separator4": 191,
    "Separator5": 173,
    "Separator8": 130,
    "splash": 533,
    "start_DataCard1": 118,
    "StarVisible13": 147,
    "StarVisible13_1": 241,
    "StarVisible13_2": 508,
    "StarVisible15": 72,
    "StarVisible15_1": 491,
    "StarVisible16": 152,
    "StarVisible16_1": 246,
    "StarVisible16_2": 513,
    "StarVisible17": 343,
    "StarVisible17_1": 435,
    "StarVisible18": 348,
    "StarVisible18_1": 440,
    "StarVisible19": 353,
    "StarVisible19_1": 445,
    "StarVisible2": 24,
    "StarVisible2_1": 206,
    "StarVisible20": 358,
    "StarVisible20_1": 450,
    "StarVisible21": 363,
    "StarVisible21_1": 455,
    "StarVisible3": 29,
    "StarVisible3_1": 211,
    "StarVisible4": 34,
    "StarVisible4_1": 216,
    "StarVisible5": 53,
    "StarVisible5_1": 472,
    "StarVisible6": 57,
    "StarVisible6_1": 476,
    "StarVisible7": 39,
    "StarVisible7_1": 221,
    "StarVisible8": 62,
    "StarVisible8_1": 481,
    "StarVisible9": 67,
    "StarVisible9_1": 486,
    "status_Column1": 318,
    "status_DataCard1": 352,
    "status_DataCard1_1": 444,
    "status_DataCard2": 121,
    "status_DataCard3": 415,
    "SubjToEmailTextInput": 528,
    "Subtitle1": 105,
    "Subtitle1_1": 289,
    "Subtitle3": 188,
    "Subtitle5": 129,
    "Subtitle9": 384,
    "SuccessModalOnlyOKButton": 33,
    "SuccessModalOnlyOKButton_1": 235,
    "tempScreenTransitionErrorFase": 19,
    "tempScreenTransitionFase1": 17,
    "tempScreenTransitionFase2": 18,
    "testGlobalVariables": 37,
    "Timer2": 0,
    "Timer3": 562,
    "Title1": 103,
    "Title1_1": 287,
    "Title12": 383,
    "Title4": 187,
    "Title5": 172,
    "Title8": 127,
    "TitleActivity": 396,
    "TitleCreateActivity": 336,
    "TitleEditAccount": 468,
    "TitleEditActivity": 428,
    "TitlePage_2": 202,
    "TitlePage_3": 143,
    "TitlePage_4": 237,
    "TitlePage_5": 504,
    "TitlePage_Choose": 280,
    "TitleViewActivity": 377,
    "Toggle_Cpf_Or_Cnpj": 9,
    "TotalHoursProject": 134,
    "TotalHoursProjectLabel": 131,
    "TxtInputLoginCnpj_Cpf": 10,
    "TxtInputLoginSenha": 12,
    "username_DataCard1": 61,
    "username_DataCard1_1": 480,
    "visualizar_atividades_colaborador": 536,
    "visualizar_evento_colaborador": 557,
    "Visualizar_Projeto_empresa": 590
  },
  "ResourcesJsonIndices": {
    "Image-business-people-rush-hour-walking-commuting-city-concept": 2,
    "Image-business-people-rush-hour-walking-commuting-city-concept-cut": 1,
    "Image-business-people-rush-hour-walking-commuting-city-concepts": 3,
    "Image-icons8-dots-loading": 4,
    "Image-image1835": 5,
    "Image-image1836": 6,
    "Image-image1838": 7,
    "Image-image1842": 8,
    "Image-image1844": 9,
    "Image-image1846": 10,
    "Image-image20128": 11,
    "Image-image20131": 12,
    "Image-image20137": 13,
    "Image-image20139": 14,
    "Image-image20179": 15,
    "Image-image20232": 16,
    "Image-image20238": 17,
    "Image-image20240": 18,
    "Image-image20242": 19,
    "Image-image20244": 20,
    "Image-image20290": 21,
    "Image-image20302": 22,
    "Image-image20310": 23,
    "Image-image20316": 24,
    "Image-image20320": 25,
    "Image-image20348": 26,
    "Image-image20354": 27,
    "Image-image20391": 28,
    "Image-image20469": 29,
    "Image-image20474": 30,
    "Image-image20479": 31,
    "Image-image20509": 32,
    "Image-image20621": 33,
    "Image-image2066": 34,
    "Image-image20706": 35,
    "Image-image20711": 36,
    "Image-image20724": 37,
    "Image-image20729": 38,
    "Image-image20750": 39,
    "Image-image2078": 40,
    "Image-image216": 41,
    "Image-image281011": 42,
    "Image-image281064": 43,
    "Image-image281080": 44,
    "Image-image281086": 45,
    "Image-image281103": 46,
    "Image-image281106": 47,
    "Image-image28789": 48,
    "Image-image28793": 49,
    "Image-image28828": 50,
    "Image-image28831": 51,
    "Image-image28852": 52,
    "Image-image28884": 53,
    "Image-image28903": 54,
    "Image-image28931": 55,
    "Image-image28942": 56,
    "Image-image28949": 57,
    "Image-image28956": 58,
    "Image-image28963": 59,
    "Image-image28970": 60,
    "Image-image28976": 61,
    "Image-image28981": 62,
    "Image-image28995": 63,
    "Image-image341155": 64,
    "Image-image341169": 65,
    "Image-image341191": 66,
    "Image-image341196": 67,
    "Image-image341202": 68,
    "Image-image341207": 69,
    "Image-image341222": 70,
    "Image-image341248": 71,
    "Image-image341254": 72,
    "Image-image341256": 73,
    "Image-image341264": 74,
    "Image-image341270": 75,
    "Image-image341280": 76,
    "Image-image341287": 77,
    "Image-image341294": 78,
    "Image-image341301": 79,
    "Image-image341308": 80,
    "Image-image341314": 81,
    "Image-image341319": 82,
    "Image-image341345": 83,
    "Image-image341358": 84,
    "Image-image341364": 85,
    "Image-image341379": 86,
    "Image-image341381": 87,
    "Image-image361394": 88,
    "Image-image361400": 89,
    "Image-image361401": 90,
    "Image-image361402": 91,
    "Image-image361403": 92,
    "Image-image361404": 93,
    "Image-image361405": 94,
    "Image-image361406": 95,
    "Image-image361411": 96,
    "Image-image361479": 97,
    "Image-image361482": 98,
    "Image-image361485": 99,
    "Image-image371504": 100,
    "Image-image371506": 101,
    "Image-image371519": 102,
    "Image-image371572": 103,
    "Image-image371584": 104,
    "Image-image371618": 105,
    "Image-image371637": 106,
    "Image-image371646": 107,
    "Image-image371662": 108,
    "Image-image371666": 109,
    "Image-image371667": 110,
    "Image-image371668": 111,
    "Image-image371669": 112,
    "Image-image381683": 113,
    "Image-image381685": 114,
    "Image-image381693": 115,
    "Image-image381699": 116,
    "Image-image381701": 117,
    "Image-image381709": 118,
    "Image-image381715": 119,
    "Image-image381718": 120,
    "Image-image381731": 121,
    "Image-image381733": 122,
    "Image-image381737": 123,
    "Image-image381746": 124,
    "Image-image381768": 125,
    "Image-image381773": 126,
    "Image-image381784": 127,
    "Image-image381789": 128,
    "Image-image381793": 129,
    "Image-image381796": 130,
    "Image-image381850": 131,
    "Image-image381863": 132,
    "Image-image381870": 133,
    "Image-image381875": 134,
    "Image-image582108": 135,
    "Image-image582167": 136,
    "Image-image8150": 137,
    "Image-SampleImage": 0,
    "Image-time-is-money-sandglass-investment-countdown-measure-concept": 138
  },
  "RuleScreenIdWithoutScreen": {},
  "TemplateVersions": {},
  "VolatileProperties": {
    "AnalysisLoadTime": 2.9673364,
    "ControlCount": {
      "347fbc906fcc4827a384a06fc53242d5": 1,
      "3b02a9f7681e4ebe8a0ed199a55799c5": 2,
      "621de0cc4b9444b2909c35573e5077f6": 2,
      "8fcf01ef466b4b9e8b209f504771e604": 16,
      "956fd0c79bbe4571aaae7899200e6c6c": 1,
      "9a83575689f34468870fdfb0440f83df": 14,
      "a7e4976df95341fea6b6fdca9e07ac48": 2,
      "button": 56,
      "circle": 2,
      "combobox": 2,
      "dataTable": 1,
      "dataTableColumn": 6,
      "datepicker": 2,
      "dropdown": 8,
      "e9a328c0cd914fc998633dc57e7f1201": 2,
      "faecc12050bb4c9ca744ac80084ea13a": 17,
      "form": 11,
      "formViewer": 3,
      "gallery": 6,
      "galleryTemplate": 6,
      "group": 8,
      "groupContainer": 5,
      "icon": 49,
      "image": 25,
      "label": 212,
      "rectangle": 38,
      "screen": 31,
      "text": 42,
      "timer": 5,
      "toggleSwitch": 1,
      "typedDataCard": 49
    },
    "DeserializationLoadTime": 10.9205531,
    "ErrorCount": 17
  },
  "WasLocalDatabaseReferencesEmpty": true
}